Workbook
Name Address: Followup!$H$2:$H$400
Name Applicable: Startup!$O$2:$O$5
Name Apprenticable: 'Base Bid'!$F$13
Name Are_they_part_of_an_AFL_CIO_Affiliated_Union?: Followup!$AH$2:$AH$400
Name Average_no_people: 'Base Bid'!$H$7
Name Base_rate_total: 'VRF and Lists'!$F$2
Name Base_Rate_Wage: 'VRF and Lists'!$F$4
Name Bid?: 'Base Bid'!#REF!
Name Bid_All: 'Base Bid'!#REF!
Name Bid_Call_for_Pricing: 'Base Bid'!#REF!
Name Bid_Clerk: 'Base Bid'!$AB$4:$AB$7
Name Bid_Ductwork?: 'Base Bid'!#REF!
Name Bid_Percentage: 'Base Bid'!#REF!
Name Bid_Piping?: 'Base Bid'!#REF!
Name Bidding_company: 'VRF and Lists'!$S$2:$S$7
Name Breakout?: 'Base Bid'!#REF!
Name Captain: 'Base Bid'!$AA$4:$AA$7
Name CBA_Fringe: 'VRF and Lists'!$F$3
Name Check_Weekly?: Followup!$AM$2:$AM$400
Name Child_Companies: Followup!$AN$2:$AN$400
Name Citizen: 'Base Bid'!$F$12
Name City: Followup!$I$2:$I$400
Name Closing_Ratio: Followup!$N$2:$N$400
Name Code: 'Quantites and Price from Mike'!$D$4:$D$117
Name Company: Followup!$C$2:$C$400
Name Company_ID: Followup!$A$2:$A$400
Name Company_Selected: 'Base Bid'!#REF!
Name Company_Status: Followup!$M$2:$M$400
Name Company_Type: Followup!$B$2:$B$400
Name Contact: Followup!$E$2:$E$400
Name Country: Followup!$P$2:$P$400
Name Days_Per_Week: 'Base Bid'!$F$5
Name DCB: Startup!$M$5
Name Do_we_bid_both_piping_and_duct_to_them?: Followup!$AG$2:$AG$400
Name Do_we_bid_to_them?: Followup!$U$2:$U$400
Name Do_we_make_them_call_for_pricing_as_we_get_no_feedback?: Followup!$Z$2:$Z$400
Name Do_we_only_bid_ductwork_to_them?: Followup!$Y$2:$Y$400
Name Do_we_only_bid_piping_to_them?: Followup!$X$2:$X$400
Name Do_we_release_breakouts_to_them?: Followup!$V$2:$V$400
Name Domain: Startup!$N$2:$N$5
Name Duct_1: 'Base Bid'!$AC$4:$AC$7
Name Duct_2: 'Base Bid'!$AD$4:$AD$7
Name Duct_breakout_no_Quantities: 'Quantites and Price from Mike'!$F$74
Name Duct_breakout_with_Quantities: 'Quantites and Price from Mike'!$G$74
Name Duct_breakout_with_Quantities_END: 'Quantites and Price from Mike'!$H$74
Name DUCT_Code: 'Quantites and Price from Mike'!$D$77:$D$100
Name Duct_Cost_by_System: 'Quantites and Price from Mike'!$E$77:$E$100
Name Duct_Price: 'Quantites and Price from Mike'!$E$74
Name DUCT_Qnt: 'Quantites and Price from Mike'!$A$77:$A$100
Name DUCT_SYSTEM: 'Quantites and Price from Mike'!$F$77:$F$100
Name DUCT_System_Name: 'Quantites and Price from Mike'!$H$77:$H$100
Name DUCT_System_Name_NO_Release: 'Quantites and Price from Mike'!$I$77:$I$100
Name DUCT_System_Name_Release_qnt: 'Quantites and Price from Mike'!$J$77:$J$100
Name DUCT_Unit: 'Quantites and Price from Mike'!$G$77:$G$100
Name Email: Followup!$F$2:$F$400
Name EQUIPMENT_Code: 'Quantites and Price from Mike'!$D$104:$D$117
Name EQUIPMENT_Cost_by_System: 'Quantites and Price from Mike'!$E$104:$E$117
Name Equipment_Price: 'Quantites and Price from Mike'!$E$101
Name EQUIPMENT_Qnt: 'Quantites and Price from Mike'!$A$104:$A$117
Name EQUIPMENT_SYSTEM: 'Quantites and Price from Mike'!$F$104:$F$117

Sheet Startup
A1: Company | B1: Delaware Cornerstone Builders, Inc. | E1: PROJECT START UP SHEET | M1: Company | N1: Domain | O1: Applicable
A2: Job Name: | E2: Job No. | M2: ----- | N2: ----- | O2: -----
A3: Mechanical Contractor (Who we have contract with) | E3: Contract Type | G3: Prime Contractor | H3: Checkbox Prime | I3: FALSE | M3: Goel Services, Inc. | N3: goelservices.com | O3: Applicable
A4: Contractor | G4: Subcontractor | H4: Checkbox Subcontractor | I4: FALSE | M4: Goel DC, LLC | N4: goeldc.com | O4: Not applicable
A5: Address 1 | E5: Form of Contract (provide copy with Startup) | M5: Delaware Cornerstone Builders, Inc. | N5: dcbuilders.com
A6: Address 2 | F6: Purchase order | H6: Checkbox PO | I6: FALSE
A7: City, State, Zip | F7: Subcontract/Contract | H7: Checkbox Subcontract | I7: FALSE
A8: Office Phone | F8: Verbal | H8: Checkbox Verbal | I8: FALSE
A9: Fax | F9: Email | H9: Checkbox Email | I9: FALSE
A10: Client Contact | F10: Other | H10: Checkbox Other | I10: FALSE
A11: Email | E11: Budget
A12: Client Phone | E12: Contract Price
A13: Send Bills to (Name) | E13: In House /Temp Labor | H13: =+F13/F12 -> #DIV/0!
A14: Email to: | E14: Material Budget | H14: =+F14/F12 -> #DIV/0!
A15: Phone # | E15: Equipment Budget | H15: Checkbox Mech Bond Yes | I15: FALSE
A16: Are they Bonded | B16: YES NO | E16: Bond Cost | H16: Checkbox Mech Bond No | I16: FALSE
A17: Sureties Name | E17: OTH/Sub Budget | H17: Bonded? | I17: =IF(F16>0,TRUE,FALSE) -> FALSE
A18: Contractor (Who mechanical has contract with) | E18: Cost Estimate | F18: =SUM(F13:G17) -> 0 | H18: 0.85 | I18: Be Conservative
E19: Average Labor Rate | F19: =+F13/F20 -> #DIV/0! | H19: Checkbox - 2nd or 3rd tier | I19: TRUE | J19: Add 5% for markup if subcontracting to Goel
A20: Contractor | E20: Labor Manhours | H20: =+F14/F13 -> #DIV/0! | I20: =1/H20 -> #DIV/0!
A21: Address 1 | E21: Projected Start Date
A22: Address 2 | E22: Projected End Date | H22: =+F22-F21 -> 0 | I22: =ROUND(+H22/365*2000,-1) -> 0
A23: City, State, Zip | F23: Is Labor to be subcontracted to Goel Services? | H23: Is Labor to be sucontracted to Goel | I23: FALSE
A24: Office Phone | E24: Owner Information
A25: Fax | E25: Prime Contract # | K25: 1000
A26: Client Contact | B26: =IF(I$19=TRUE,"n/a","") -> n/a | E26: Owner Name
A27: Email | B27: =IF(I$19=TRUE,"n/a","") -> n/a | E27: Address
A28: Client Phone | B28: =IF(I$19=TRUE,"n/a","") -> n/a | E28: Address
A29: Prime Contractor | E29: City, State, Zip
A30: Contractor | E30: Phone
A31: Address | E31: Fax
A32: Address | E32: Client Contact
A33: City, State, Zip | E33: Email
A34: Phone | E34: Client Phone
A35: Fax | E35: Certified Payroll
A36: Client Contact/PM | F36: Yes - Include CP Wage Decision # and copy with startup | H36: Checkbox CP Yes | I36: FALSE
A37: Email | E37: Wage Decision #
A38: Client Phone | F38: No | H38: Checkbox CP No | I38: FALSE
A39: Are they Bonded | B39: YES NO | E39: Wage (Excluding Fringe)
A40: Sureties Name | E40: Fringe (min fringe = $3.93)
A41: Site Information | E41: ="Wage Rate adds paid hoildays - +A" -> Wage Rate adds paid hoildays - +A
A42: Location Name | B42: =+B2 -> 0 | E42: Send Certified Payrolls to:
A43: Address 1 | E43: Contractor | H43: Checkbox Prime Bond Yes | I43: FALSE
A44: Address 2 | E44: Address | H44: Checkbox Prime Bond No | I44: FALSE
A45: City, State, Zip Code | E45: Address
A46: Super Contact/PM | E46: City, State, Zip
A47: Super Email | E47: Phone
A48: Super Phone | E48: Fax
A49: Prime Contractor's OCIP | E49: Attn (Name)
B50: Yes | E50: Email to send to:
B51: No | E51: CP. Phone | H51: Checkbox Email | I51: FALSE
A52: Drawings conformed on MIKE to show all scope, VE's etc. and converted to PDF. Printout included with estimates from MIKE per schedule | E52: Send via email or mail
B53: Provided | F53: Email
B54: Not Provided | F54: Mail
A55: Bond to be provided | E55: Does subcontract discuss pre-insulated blocks, vitaulic fittings, painting and jacketing requirements? | H55: Checkbox Mail | I55: FALSE
B56: Yes | F56: Yes | H56: Checkbox OCIP YES | I56: FALSE
B57: No | F57: No: If not risk? | H57: Checkbox OCIP No | I57: FALSE
A58: Attendence, Travel, or Parking Expense? | E58: Check all that apply | H58: Attendance | I58: FALSE
B59: Yes (If yes - please identify agreements) | F59: Mechanical Insulator | H59: Checkbox Bond Yes | I59: FALSE
F60: Laborer - Common or Unskilled | H60: Checkbox Bond No | I60: FALSE
F61: Carpenter | H61: Checkbox Mechanical Insulation | I61: FALSE
F62: Haz Mat Handler (Removal of existing insulation) | H62: Checkbox Carpenter | I62: FALSE
F63: Helper | H63: Checkbox Laborer - Common or Unskilled | I63: FALSE
A64: Is project Tax exempt? | E64: Other | H64: Checkbox HazMat | I64: FALSE
B65: Yes (If yes - attach certificate) | E65: SOV provided? | G65: Schedule provided by Mech? | H65: Checkbox Other 1 | I65: FALSE
B66: No | E66: Yes | G66: Yes | H66: Checkbox Other 2 | I66: FALSE
A67: Other Special Instructions (please identify any special rates; etc..) | H67: MIKE info provided | I67: FALSE
E68: No | G68: No | H68: MIKE info not provided | I68: FALSE
H69: Tax exempt - yes | I69: TRUE
H70: Tax exempt - no | I70: FALSE
A71: Date | C71: Name/ Signature | E71: Insulation Division Manager Signature

Sheet Base Bid
A1: BID Estimate # | B1: IDC6098 | C1: Bid Name | D1: SCU Replacement Basement to 6th Floor, East & West | F1: Team | G1: MIKE Estimate | H1: =+H48 -> 43837.68 | I1: PJ Estimate | J1: =PJ_Estimate -> 47600
A2: Bid Date | B2: 46141 | C2: Company Bidding | D2: Goel Services, Inc. | F2: Bil Shams | G2: Cost per Hr | H2: =+I48 -> 89.906848 | I2: Cost per Hr | J2: =+I47 -> 97.62
A3: Captain | B3: Bid Clerk | C3: Assistant Estimator | D3: Margin | E3: Hours and Wages (do not correct till you add MIKE info) | G3: PLA | H3: No | I3: Lifts | M3: Wage | Z3: Team | AA3: Captain | AB3: Bid Clerk | AC3: Duct 1 | AD3: Duct 2 | AE3: Hydronic 1 | AF3: Hydronic 2 | AG3: Plumbing 1 | AH3: Plumbing 2
A4: =_xlfn.XLOOKUP(F$2,Team_list,Captain) -> Bil Shams | B4: John Alex Lopez | C4: =_xlfn.XLOOKUP(F$2,Team_list,Bid_Clerk) -> Mark Tan | D4: 0.25 | E4: Hours per day | F4: 8 | G4: Category | H4: ---- | I4: Lifts | J4: No | M4: Wage Rate Year | N4: Wage Rate | O4: Wage Rate Fringe | P4: Wage Rate Total | Q4: Wage As of | R4: Wage Rate Next update | S4: Wage Rate List | Z4: ---- | AA4: ---- | AB4: ---- | AC4: ---- | AD4: ---- | AE4: ---- | AF4: ---- | AG4: ---- | AH4: ----
A5: What State is this project in? | B5: DC | C5: Project Type | D5: New Construction with deep shoring - small | E5: Days per Week | F5: 5 | G5: MBE or preference | H5: ---- | I5: % of people on Lifts we provide | J5: 1 | M5: NON-SCALE | N5: 30 | O5: 7.29 | P5: =+N5+O5 -> 37.29 | Q5: 46084 | R5: No | S5: =IF(M5="","",CONCATENATE(M5," - W: ($",N5," + F: $",O5,") = Total of $",P5)) -> NON-SCALE - W: ($30 + F: $7.29) = Total of $37.29 | Z5: Wilder Rodriguez | AA5: Wilder Rodriguez | AB5: Hassan Riaz | AC5: John Carlo Orpilla | AE5: Jonathan Bruce | AF5: Brian Angelo Limon | AG5: Hennan Berberio | AH5: Mark Chua
E6: Hours (per week) | F6: =+F4*F5 -> 40 | G6: Hours | I6: Lift cost average rental per 4 weeks | J6: 550 | L6: scale | M6: 2026 - DC/Federal in DC/CITIZEN | N6: 40.77 | O6: 20.17 | P6: =+N6+O6 -> 60.94 | Q6: 46074 | R6: Yes | S6: =IF(M6="","",CONCATENATE(M6," - W: ($",N6," + F: $",O6,") = Total of $",P6)) -> 2026 - DC/Federal in DC/CITIZEN - W: ($40.77 + F: $20.17) = Total of $60.94 | Z6: Bil Shams | AA6: Bil Shams | AB6: Mark Tan | AC6: Marc Maniago | AD6: Oliver Crucero | AE6: Maristella Malamug | AF6: Kevin Strauss | AG6: Ralph Resare | AH6: Hugh Belangel
E7: GSF of Building | G7: Number of personnel | H7: =ROUND(+J19/B12/(1950/12),2) -> 1.5 | I7: Total for lifts on this project | J7: =+Lift_percentage*Lift_cost*Project_Months*(4.4/4)*Average_no_people -> 1815 | L7: scale | M7: 2026 - Maryland/Federal | N7: 40.77 | O7: 20.42 | P7: =+N7+O7 -> 61.19 | Q7: 46074 | R7: Yes | S7: =IF(M7="","",CONCATENATE(M7," - W: ($",N7," + F: $",O7,") = Total of $",P7)) -> 2026 - Maryland/Federal - W: ($40.77 + F: $20.42) = Total of $61.19 | Z7: Mike Robberts | AA7: Mike Roberts | AB7: Rhal Dumol | AC7: Wesley Morris | AD7: Gerald Ordonez | AE7: Jeremee Camat | AG7: Joel Simplina | AH7: Junel Neri
A8: Is the job scale | B8: NON-SCALE - W: ($30 + F: $7.29) = Total of $37.29 | E8: Does O/CCIP cover WC? | F8: No | G8: Backcheck (hours) | H8: =ROUND(+B12*1950/12*H7,0) -> 488 | I8: Parking | L8: scale | M8: 2026 - Virginia | N8: 39.27 | O8: 18.67 | P8: =+N8+O8 -> 57.94 | Q8: 46074 | R8: Yes | S8: =IF(M8="","",CONCATENATE(M8," - W: ($",N8," + F: $",O8,") = Total of $",P8)) -> 2026 - Virginia - W: ($39.27 + F: $18.67) = Total of $57.94
E9: Wage | F9: =_xlfn.XLOOKUP(Project_Wage_Rate,Wage_Rate_List,Wage_Rate) -> 30 | G9: Material Escalation | I9: Parking | J9: Yes | L9: scale | M9: 2024 - MD Prevail | N9: 39.27 | O9: 19.42 | P9: =+N9+O9 -> 58.69 | Q9: 46074 | R9: Yes | S9: =IF(M9="","",CONCATENATE(M9," - W: ($",N9," + F: $",O9,") = Total of $",P9)) -> 2024 - MD Prevail - W: ($39.27 + F: $19.42) = Total of $58.69
A10: When will our work begin mm/YY (you can override) | B10: =EDATE(B2,B13) -> 46324 | C10: TOTAL BIDDING LABOR RATE | D10: =+labor_rate -> 51.7 | E10: Fringe | F10: =_xlfn.XLOOKUP(Project_Wage_Rate,Wage_Rate_List,Wage_Rate_Fringe) -> 7.29 | G10: Escalation on materials per Year | H10: 0.04 | I10: % of people on that will park | J10: 1 | L10: scale | M10: 2024 | N10: 40.02 | O10: 19.67 | P10: =+P11+0.75 -> 60.19 | Q10: 45931 | R10: Yes | S10: =IF(M10="","",CONCATENATE(M10," - W: ($",N10," + F: $",O10,") = Total of $",P10)) -> 2024 - W: ($40.02 + F: $19.67) = Total of $60.19
A11: When will our work end MM/YY (you can override) | B11: =EDATE(B10,B12-1) -> 46355 | C11: PARKING PER HOUR | D11: =IF(Parking="Yes",Parking_cost/Hours_per_day,0) -> 3.125 | E11: Totals | F11: =+F9+F10 -> 37.29 | G11: Total escalation based on year work will begin | H11: =(YEAR(B11)-YEAR(B2))*H10 -> 0 | I11: Parking Cost per Day - we reimburse | J11: 25 | L11: scale | M11: 2024 | N11: 40.02 | O11: 19.67 | P11: =+P12+0.75 -> 59.44 | Q11: 45931 | R11: Yes | S11: =IF(M11="","",CONCATENATE(M11," - W: ($",N11," + F: $",O11,") = Total of $",P11)) -> 2024 - W: ($40.02 + F: $19.67) = Total of $59.44
A12: Duration of Project - Months | B12: 2 | C12: LIFT PER HOUR | D12: =IF(Lifts_Needed="Yes",IFERROR(Total_Lift/Total_Hours,0),0) -> 0 | E12: Citizen Project | F12: No | G12: Sales Tax Applicable | H12: Yes | L12: scale | M12: 2023 | N12: 40.02 | O12: 19.67 | P12: =+P13+0.75 -> 58.69 | Q12: 45931 | R12: Yes | S12: =IF(M12="","",CONCATENATE(M12," - W: ($",N12," + F: $",O12,") = Total of $",P12)) -> 2023 - W: ($40.02 + F: $19.67) = Total of $58.69
A13: Start in # of months from bid | B13: 6 | C13: TOTAL LABOR PER HR WITH PARKING AND LIFTS | D13: =+D10+D11+D12 -> 54.825 | E13: Apprenticeable job | F13: Yes | G13: Sales Tax % | H13: =_xlfn.XLOOKUP(Project_State,Rate_State,Sales_Tax_by_state) -> 0.06 | L13: scale | M13: 2021 | N13: 39.27 | O13: 18.67 | P13: =+N13+O13 -> 57.94 | Q13: 45200 | R13: Yes | S13: =IF(M13="","",CONCATENATE(M13," - W: ($",N13," + F: $",O13,") = Total of $",P13)) -> 2021 - W: ($39.27 + F: $18.67) = Total of $57.94
A14: INPUT FIELD | L14: scale | M14: 2019 | N14: 38.01 | O14: 17.62 | P14: =+N14+O14 -> 55.63 | Q14: 44287 | R14: Yes | S14: =IF(M14="","",CONCATENATE(M14," - W: ($",N14," + F: $",O14,") = Total of $",P14)) -> 2019 - W: ($38.01 + F: $17.62) = Total of $55.63
A15: System | B15: Duct 1 | C15: Duct 2 | D15: Hydronic 1 | E15: Hydronic 2 | F15: Plumbing 1 | G15: Plumbing 2 | H15: VRF (only include if not in hydronic) | I15: Equipment (only include if not in MIKE) | J15: MIKE Estimate Totals | L15: scale | M15: 2017 | N15: 35.13 | O15: 16.22 | P15: =+N15+O15 -> 51.35 | Q15: 43556 | R15: Yes | S15: =IF(M15="","",CONCATENATE(M15," - W: ($",N15," + F: $",O15,") = Total of $",P15)) -> 2017 - W: ($35.13 + F: $16.22) = Total of $51.35
A16: Take off Personnel | B16: =IFERROR(_xlfn.XLOOKUP($F$2,Team_list,Duct_1),"") -> Marc Maniago | C16: =IFERROR(_xlfn.XLOOKUP($F$2,Team_list,Duct_2),"") -> Oliver Crucero | D16: =IFERROR(_xlfn.XLOOKUP(F$2,Team_list,Hydronic_1),"") -> Maristella Malamug | E16: =IFERROR(_xlfn.XLOOKUP(F$2,Team_list,Hydronic_2),"") -> Kevin Strauss | F16: =IFERROR(_xlfn.XLOOKUP(F$2,Team_list,Plumbing_1),"") -> Ralph Resare | G16: =IFERROR(_xlfn.XLOOKUP(F$2,Team_list,Plumbing_2),"") -> Hugh Belangel | L16: scale | M16: 2015 | N16: 35.03 | O16: 15.32 | P16: =+N16+O16 -> 50.35 | Q16: 42826 | R16: Yes | S16: =IF(M16="","",CONCATENATE(M16," - W: ($",N16," + F: $",O16,") = Total of $",P16)) -> 2015 - W: ($35.03 + F: $15.32) = Total of $50.35
A17: MIKE Estimate # | B17: 7969.02 | D17: 7969.04 | L17: scale | M17: 2013 | N17: 33.13 | O17: 13.6 | P17: =+N17+O17 -> 46.73 | Q17: 42095 | R17: Yes | S17: =IF(M17="","",CONCATENATE(M17," - W: ($",N17," + F: $",O17,") = Total of $",P17)) -> 2013 - W: ($33.13 + F: $13.6) = Total of $46.73
A18: Materials without escalation | B18: 3268.95 | D18: 5187.54 | J18: =IF(B$23="yes",B18,C18)+IF(D$23="yes",D18,E18)+IF(F$23="yes",F18,G18)+H18+I18 -> 8456.49 | S18: =IF(M18="","",CONCATENATE(M18," - W: ($",N18," + F: $",O18,") = Total of $",P18))
A19: Labor Hours | B19: 228.52 | D19: 259.07 | J19: =IF(B$23="yes",B19,C19)+IF(D$23="yes",D19,E19)+IF(F$23="yes",F19,G19)+H19+I19 -> 487.59 | S19: =IF(M19="","",CONCATENATE(M19," - W: ($",N19," + F: $",O19,") = Total of $",P19))
A20: TOTAL PRICE per MIKE | B20: 19515.92 | D20: 24321.76 | J20: =IF(B$23="yes",B20,C20)+IF(D$23="yes",D20,E20)+IF(F$23="yes",F20,G20)+H20+I20 -> 43837.68
A21: Quantity (LF/SF) | B21: 5455.98 | D21: 1129.84
A22: Quantity (This Sheet) | B22: =IF(B23="Yes",B21,C21) -> 5455.98 | D22: =IF(D23="Yes",D21,E21) -> 1129.84 | F22: =IF(F23="Yes",F21,G21) -> 0
A23: Who was used | B23: Yes | C23: No | D23: Yes | E23: No | F23: Yes | G23: No
A24: Labor per hour | B24: =IF(B19+C19=0,"",+Total_Wage-Parking_Per_Hour) -> 51.7 | D24: =IF(D19+E19=0,"",+Total_Wage-Parking_Per_Hour) -> 51.7 | F24: =IF(F19+G19=0,"",+Total_Wage-Parking_Per_Hour) | H24: =IF(H19=0,"",+Total_Wage-Parking_Per_Hour) | I24: =IF(I19=0,"",+Total_Wage-Parking_Per_Hour) | J24: =IF(J19=0,0,+Total_Wage-Parking_Per_Hour) -> 51.7
A25: Parking per hour | B25: =IF(Parking="Yes",Parking_Per_Hour,"") -> 3.125 | D25: =IF(Parking="Yes",Parking_Per_Hour,"") -> 3.125 | F25: =IF(Parking="Yes",Parking_Per_Hour,"") -> 3.125 | H25: =IF(Parking="Yes",Parking_Per_Hour,"") -> 3.125 | I25: =IF(Parking="Yes",Parking_Per_Hour,"") -> 3.125 | J25: =IF(J19=0,0,Parking_Per_Hour) -> 3.125
A26: Lifts per hour | B26: =IF(Lifts_Needed="Yes",Lifts_Per_Hour,"") | D26: =IF(Lifts_Needed="Yes",Lifts_Per_Hour,"") | F26: =IF(Lifts_Needed="Yes",Lifts_Per_Hour,"") | H26: =IF(Lifts_Needed="Yes",Lifts_Per_Hour,"") | I26: =IF(Lifts_Needed="Yes",Lifts_Per_Hour,"") | J26: =IF(J19=0,0,Lifts_Per_Hour) -> 0
A27: Materials/hour w escal+tax | B27: =IFERROR(IF(B23="Yes",B18/B19,C18/B19),"") -> 14.304875 | D27: =IFERROR(IF(D23="Yes",D18/D19,E18/D19),"") -> 20.0237 | F27: =IFERROR(IF(F23="Yes",F18/F19,G18/F19),"") | H27: =IFERROR(H18/H19,"") | I27: =IFERROR(I18/I19,"") | J27: =IFERROR(J18/J19,0) -> 17.343444
A28: Material Escalation | B28: =IFERROR(IF(B27="","",B27*Material_Escalation),"") -> 0 | D28: =IFERROR(IF(D27="","",D27*Material_Escalation),"") -> 0 | F28: =IFERROR(IF(F27="","",F27*Material_Escalation),"") | H28: =IFERROR(IF(H27="","",H27*Material_Escalation),"") | I28: =IFERROR(IF(I27="","",I27*Material_Escalation),"") | J28: =IFERROR(IF(J27="","",J27*Material_Escalation),"") -> 0
A29: Material Sales Tax | B29: =IFERROR((IF(B27="","",(B27+B28)*Sales_tax_percent)),"") -> 0.85829249 | D29: =IFERROR((IF(D27="","",(D27+D28)*Sales_tax_percent)),"") -> 1.201422 | F29: =IFERROR((IF(F27="","",(F27+F28)*Sales_tax_percent)),"") | H29: =IFERROR((IF(H27="","",(H27+H28)*Sales_tax_percent)),"") | I29: =IFERROR((IF(I27="","",(I27+I28)*Sales_tax_percent)),"") | J29: =IFERROR((IF(J27="","",(J27+J28)*Sales_tax_percent)),"") -> 1.0406067
A30: Total Cost per hour | B30: =IF(B24="","",IFERROR(+SUM(B24:C29),"")) -> 69.988167 | D30: =IF(D24="","",IFERROR(+SUM(D24:E29),"")) -> 76.050122 | F30: =IF(F24="","",IFERROR(+SUM(F24:G29),"")) | H30: =IF(H24="","",IFERROR(+SUM(H24:H29),"")) | I30: =IF(I24="","",IFERROR(+SUM(I24:I29),"")) | J30: =IF(J24="","",IFERROR(+SUM(J24:J29),"")) -> 73.209051
A31: Margin | B31: =IFERROR(+B30/(1-Margin)-B30,"") -> 23.329389 | D31: =IFERROR(+D30/(1-Margin)-D30,"") -> 25.350041 | F31: =IFERROR(+F30/(1-Margin)-F30,"") | H31: =IF(H25="","",IFERROR(+SUM(H25:H30),"")) -> 3.125 | I31: =IF(I25="","",IFERROR(+SUM(I25:I30),"")) -> 3.125 | J31: =IFERROR(+J30/(1-Margin)-J30,"") -> 24.403017
A32: Cost per hour with Margin | B32: =IFERROR(+B30+B31,"") -> 93.317556 | D32: =IFERROR(+D30+D31,"") -> 101.40016 | F32: =IFERROR(+F30+F31,"") | H32: =IFERROR(+H30/(1-Margin),"") | I32: =IFERROR(+I30/(1-Margin),"") | J32: =IFERROR(+J30+J31,"") -> 97.612068
A33: Cost based on math above | B33: =IFERROR(+(B30*B19)/(1-Margin),"") -> 21324.928 | D33: =IFERROR(+(D30*D19)/(1-Margin),"") -> 26269.74 | F33: =IFERROR(+(F30*F19)/(1-Margin),"") | H33: =IFERROR(+H32*H19,"") | I33: =IFERROR(+I32*I19,"") | J33: =IFERROR(ROUNDUP(+(J30*J19)/(1-Margin),-3),"") -> 48000
C36: Duct | D36: Hydronic | E36: Plumbing | F36: VRF | G36: Equipment | H36: Totals | I36: Cost per hour
A37: Labor Hours | C37: =IF(B23="Yes",B19,C19) -> 228.52 | D37: =IF(D23="Yes",D19,E19) -> 259.07 | E37: =IF(F23="Yes",F19,G19) -> 0 | F37: =+H19 -> 0 | G37: =+I19 -> 0 | H37: =SUM(C37:G37) -> 487.59
A38: Labor cost per hour | C38: =+Wage_Rate_Composite -> 51.7 | D38: =+Wage_Rate_Composite -> 51.7 | E38: =+Wage_Rate_Composite -> 51.7 | F38: =+Wage_Rate_Composite -> 51.7 | G38: =+Wage_Rate_Composite -> 51.7 | H38: =+Wage_Rate_Composite -> 51.7
A39: =+A25 -> Parking per hour | C39: =+Parking_Per_Hour -> 3.125 | D39: =+Parking_Per_Hour -> 3.125 | E39: =+Parking_Per_Hour -> 3.125 | F39: =+Parking_Per_Hour -> 3.125 | G39: =+Parking_Per_Hour -> 3.125 | H39: =+Parking_Per_Hour -> 3.125
A40: =+A26 -> Lifts per hour | C40: =+Lifts_Per_Hour -> 0 | D40: =+Lifts_Per_Hour -> 0 | E40: =+Lifts_Per_Hour -> 0 | F40: =+Lifts_Per_Hour -> 0 | G40: =+Lifts_Per_Hour -> 0 | H40: =+Lifts_Per_Hour -> 0
A41: Labor Total (no Margin) | C41: =IFERROR(+C37*SUM(C38:C40),"") -> 12528.609 | D41: =IFERROR(+D37*SUM(D38:D40),"") -> 14203.513 | E41: =IFERROR(+E37*SUM(E38:E40),"") -> 0 | F41: =IFERROR(+F37*SUM(F38:F40),"") -> 0 | G41: =IFERROR(+G37*SUM(G38:G40),"") -> 0 | H41: =IFERROR(+H37*SUM(H38:H40),"") -> 26732.122 | I41: =IFERROR(ROUNDUP(SUM(H38:H40)/H37,2),0) -> 0.12
A42: Materials (without escalations or profit) | C42: =IF(B23="Yes",B18,C18) -> 3268.95 | D42: =IF(D23="Yes",D18,E18) -> 5187.54 | E42: =IF(F23="Yes",F18,G18) -> 0 | F42: =+H18 -> 0 | G42: =+I18 -> 0 | H42: =SUM(C42:G42) -> 8456.49 | I42: =IFERROR(ROUNDUP((+SUM(H42:H44))/H37,2),0) -> 18.39
A43: Material Escalation | B43: =+Material_Escalation -> 0 | C43: =+C42*Material_Escalation -> 0 | D43: =+D42*Material_Escalation -> 0 | E43: =+E42*Material_Escalation -> 0 | F43: =+F42*Material_Escalation -> 0 | G43: =+G42*Material_Escalation -> 0 | H43: =+H42*Material_Escalation -> 0
A44: Material Sales Tax | B44: =+Sales_tax_percent -> 0.06 | C44: =(+C42+C43)*Sales_tax_percent -> 196.137 | D44: =(+D42+D43)*Sales_tax_percent -> 311.2524 | E44: =(+E42+E43)*Sales_tax_percent -> 0 | F44: =(+F42+F43)*Sales_tax_percent -> 0 | G44: =(+G42+G43)*Sales_tax_percent -> 0 | H44: =(+H42+H43)*Sales_tax_percent -> 507.3894
A45: Subtotal | C45: =SUM(C41:C44) -> 15993.696 | D45: =SUM(D41:D44) -> 19702.305 | E45: =SUM(E41:E44) -> 0 | F45: =SUM(F41:F44) -> 0 | G45: =SUM(G41:G44) -> 0 | H45: =SUM(H41:H44) -> 35696.001 | I45: =IFERROR(ROUNDUP(+H45/H37,2),0) -> 73.21
A46: Margin | C46: =Margin -> 0.25 | H46: =IFERROR(+I46*J19,"") -> 11902.072 | I46: =IFERROR(ROUNDUP(-+I45+I45/(1-Margin),2),"") -> 24.41
A47: Bid Price - PJ Calculation | H47: =IFERROR(ROUNDUP(+I47*H37,-2),"") -> 47600 | I47: =IFERROR(+I45+I46,"") -> 97.62
A48: Bid Price - MIKE Calculation | H48: =+J20 -> 43837.68 | I48: =IFERROR(+H48/H37,0) -> 89.906848
A49: FINAL PRICE

Sheet Budget
A1: ($) | B1: ($) | C1: ($) | D1: ($) | E1: ($) | F1: HRS | G1: LF | H1: ($) | I1: ($) | J1: ($) | K1: ($) | L1: ($) | M1: HRS | N1: SF | O1: ($) | P1: ($) | Q1: ($) | R1: ($) | S1: ($) | T1: HRS | U1: LF
A2: Hydronic Pipe - Total In House/Temp Labor Budget | B2: Hydronic Pipe - Total Material Budget | C2: Hydronic Pipe - Total Equipment Budget | D2: Hydronic Pipe - Total Bond Budget | E2: Hydronic Pipe - Total Other/Sub Budget | F2: Hydronic Pipe - Total Labor Manhours | G2: Hydronic Pipe - Quantity Pipe (LF) | H2: Duct - Total In House/Temp Labor Budget | I2: Duct - Total Material Budget | J2: Duct - Total Equipment Budget | K2: Duct - Total Bond Budget | L2: Duct - Total Other/Sub Budget | M2: Duct - Total Labor Manhours | N2: Duct - Quantity Duct (SF) | O2: Plumbing - Total In House/Temp Labor Budget | P2: Plumbing - Total Material Budget | Q2: Plumbing - Total Equipment Budget | R2: Plumbing - Total Bond Budget | S2: Plumbing - Total Other/Sub Budget | T2: Plumbing - Total Labor Manhours | U2: Plumbing - Quantity Pipe (LF) | V2: initial Labor Hour Budget | W2: Total Labor Hours Budget | X2: Total material Budget
A8: Budget
A9: Contract Price
A10: In House /Temp Labor
A11: Material Budget
A12: Equipment Budget
A13: Bond Cost
A14: OTH/Sub Budget
A15: Cost Estimate | C15: =SUM(C10:C14) -> 0

Sheet Labor Costs
A1: NOT FOR RELEASE - BIDDING ONLY - USE PM RATES | H1: WAGE RATE | I1: =IFERROR(labor_rate,"") -> 51.7
A2: Category | B2: Reg | C2: OT | D2: Qnt | E2: Extended | F2: Hrs | H2: Company | I2: =+'Base Bid'!D2 -> Goel Services, Inc.
A3: Asbestos Insulation Worker - Citizen/Prev Wage | B3: ='Labor Costs Worksheet'!H35 -> 47.69 | C3: ='Labor Costs Worksheet'!I35 -> 64.5 | D3: =IF(H4='Base Bid'!S5,"",IF(Project_Wage_Rate='Base Bid'!S5,"",No_Workers)) | E3: =IFERROR(IF(D3="","",+B3*40+(Hours_Per_week-40)*C3)*D3,"") | F3: =IF(D3="","",+D3*Hours_Per_week) | H3: Wage Rate | L3: =+B3 -> 47.69
A4: Asbestos Insulation Worker - Non Scale | B4: =+'Labor Costs Worksheet'!J35 -> 47.69 | C4: =+'Labor Costs Worksheet'!K35 -> 64.5 | D4: =IF(H4='Base Bid'!S5,(IF(Project_Wage_Rate='Base Bid'!S5,No_Workers,"")),"") -> 1 | E4: =IFERROR(IF(D4="","",+B4*40+(Hours_Per_week-40)*C4)*D4,"") -> 1907.6 | F4: =IF(D4="","",+D4*Hours_Per_week) -> 40 | H4: ='Base Bid'!$B$8 -> NON-SCALE - W: ($30 + F: $7.29) = Total of $37.29 | L4: =+B11 -> 35.75
A5: Working Asbestos Insulation Foreman (S5) | B5: ='Labor Costs Worksheet'!L35 -> 76.68 | C5: ='Labor Costs Worksheet'!M35 -> 104.91 | D5: =IF('Base Bid'!H8>5000,IF(Project_Wage_Rate='Base Bid'!S5,"",No_Foreman),"") | E5: =IFERROR(IF(D5="","",+B5*40+(Hours_Per_week-40)*C5)*D5,"") | F5: =IF(D5="","",+D5*Hours_Per_week) | L5: =+L3-L4 -> 11.94
A6: Working Asbestos Insulation Foreman (S4) | B6: ='Labor Costs Worksheet'!N35 -> 75.56 | C6: ='Labor Costs Worksheet'!O35 -> 103.79 | D6: =IFERROR(IF('Base Bid'!H8>4000,IF(Project_Wage_Rate='Base Bid'!S5,"",No_Foreman),"")-D5,"") | E6: =IFERROR(IF(D6="","",+B6*40+(Hours_Per_week-40)*C6)*D6,"") | F6: =IF(D6="","",+D6*Hours_Per_week) | H6: ='Base Bid'!A5 -> What State is this project in? | I6: ='Base Bid'!B5 -> DC | L6: =+L5*1950 -> 23283
A7: Working Asbestos Insulation Foreman (S3) | B7: ='Labor Costs Worksheet'!P35 -> 74.45 | C7: ='Labor Costs Worksheet'!Q35 -> 102.67 | D7: =IF('Base Bid'!H8<3999,IF(Project_Wage_Rate='Base Bid'!S5,"",No_Foreman),"") | E7: =IFERROR(IF(D7="","",+B7*40+(Hours_Per_week-40)*C7)*D7,"") | F7: =IF(D7="","",+D7*Hours_Per_week) | H7: ='Base Bid'!E12 -> Citizen Project | I7: ='Base Bid'!F12 -> No | L7: =20*L6 -> 465660
A8: Working Asbestos Insulation Foreman (S2) | B8: ='Labor Costs Worksheet'!R35 -> 50.12 | C8: ='Labor Costs Worksheet'!S35 -> 66.74 | D8: =IF(Project_Wage_Rate='Base Bid'!S5,No_Foreman,"") -> 1 | E8: =IFERROR(IF(D8="","",+B8*40+(Hours_Per_week-40)*C8)*D8,"") -> 2004.8 | F8: =IF(D8="","",+D8*Hours_Per_week) -> 40 | H8: ='Base Bid'!G7 -> Number of personnel | I8: ='Base Bid'!H7 -> 1.5
A9: Working Asbestos Insulation Foreman (S1) | B9: ='Labor Costs Worksheet'!T35 -> 49 | C9: ='Labor Costs Worksheet'!U35 -> 65.62 | E9: =IFERROR(IF(D9="","",+B9*40+(Hours_Per_week-40)*C9)*D9,"") | F9: =IF(D9="","",+D9*Hours_Per_week) | H9: ='Base Bid'!E6 -> Hours (per week) | I9: ='Base Bid'!F6 -> 40
A10: Safety Inspector (S5) | B10: ='Labor Costs Worksheet'!X35 -> 78.01 | C10: ='Labor Costs Worksheet'!Y35 -> 102.23 | E10: =IFERROR(IF(D10="","",+B10*40+(Hours_Per_week-40)*C10)*D10,"") | F10: =IF(D10="","",+D10*Hours_Per_week) | H10: Duration in Months | I10: ='Base Bid'!B12 -> 2
A11: Asbestos Apprentice Step 1 | B11: ='Labor Costs Worksheet'!Z35 -> 35.75 | C11: ='Labor Costs Worksheet'!AA35 -> 46.59 | E11: =IFERROR(IF(D11="","",+B11*40+(Hours_Per_week-40)*C11)*D11,"") | F11: =IF(D11="","",+D11*Hours_Per_week) | H11: ='Base Bid'!G8 -> Backcheck (hours) | I11: ='Base Bid'!H8 -> 488
A12: Asbestos Apprentice Step 2 | B12: ='Labor Costs Worksheet'!AB35 -> 36.14 | C12: ='Labor Costs Worksheet'!AC35 -> 47.17 | E12: =IFERROR(IF(D12="","",+B12*40+(Hours_Per_week-40)*C12)*D12,"") | F12: =IF(D12="","",+D12*Hours_Per_week) | H12: ='Base Bid'!E13 -> Apprenticeable job | I12: ='Base Bid'!F13 -> Yes
A13: Asbestos Apprentice Step 3 | B13: ='Labor Costs Worksheet'!AD35 -> 36.14 | C13: ='Labor Costs Worksheet'!AE35 -> 47.17 | D13: =No_Apprentices -> 0 | E13: =IFERROR(IF(D13="","",+B13*40+(Hours_Per_week-40)*C13)*D13,"") -> 0 | F13: =IF(D13="","",+D13*Hours_Per_week) -> 0
A14: Asbestos Apprentice Step 4 | B14: ='Labor Costs Worksheet'!AF35 -> 36.14 | C14: ='Labor Costs Worksheet'!AG35 -> 47.17 | E14: =IFERROR(IF(D14="","",+B14*40+(Hours_Per_week-40)*C14)*D14,"") | F14: =IF(D14="","",+D14*Hours_Per_week) | H14: ='Base Bid'!E8 -> Does O/CCIP cover WC? | I14: ='Base Bid'!F8 -> No
A15: Asbestos Apprentice Step 5 | B15: ='Labor Costs Worksheet'!AH35 -> 36.14 | C15: ='Labor Costs Worksheet'!AI35 -> 47.17 | E15: =IFERROR(IF(D15="","",+B15*40+(Hours_Per_week-40)*C15)*D15,"") | F15: =IF(D15="","",+D15*Hours_Per_week) | H15: Ratio 1: | I15: 2.5
A16: Asbestos Apprentice Step 6 | B16: =+'Labor Costs Worksheet'!AJ35 -> 36.14 | C16: =+'Labor Costs Worksheet'!AK35 -> 47.17 | E16: =IFERROR(IF(D16="","",+B16*40+(Hours_Per_week-40)*C16)*D16,"")
A17: Asbestos Apprentice Step 7 | B17: ='Labor Costs Worksheet'!AL35 -> 37.61 | C17: ='Labor Costs Worksheet'!AM35 -> 49.38 | E17: =IFERROR(IF(D17="","",+B17*40+(Hours_Per_week-40)*C17)*D17,"") | F17: =IF(D17="","",+D17*Hours_Per_week) | H17: Foreman | I17: 1
A18: Asbestos Apprentice Step 8 | B18: ='Labor Costs Worksheet'!AN35 -> 40.97 | C18: ='Labor Costs Worksheet'!AO35 -> 54.42 | E18: =IFERROR(IF(D18="","",+B18*40+(Hours_Per_week-40)*C18)*D18,"") | F18: =IF(D18="","",+D18*Hours_Per_week) | H18: Workers | I18: =IF(I8=0,1,ROUND(+I8-I17-I19,0)) -> 1
A19: Project Manager (S10) | B19: ='Labor Costs Worksheet'!V35 -> 83.55 | C19: ='Labor Costs Worksheet'!W35 -> 107.83 | D19: 0.1 | E19: =IFERROR(IF(D19="","",+B19*40+(Hours_Per_week-40)*C19)*D19,"") -> 334.2 | F19: =IF(D19="","",+D19*Hours_Per_week) -> 4 | H19: Apprentices | I19: =ROUND(+I8/(1+I15),0) -> 0
A20: =+'Labor Costs Worksheet'!AP4 -> Ops Manager | B20: ='Labor Costs Worksheet'!AP35 -> 83.61 | C20: ='Labor Costs Worksheet'!AQ35 -> 107.83 | D20: 0.1 | E20: =IFERROR(IF(D20="","",+B20*40+(Hours_Per_week-40)*C20)*D20,"") -> 334.44 | F20: =IF(D20="","",+D20*Hours_Per_week) -> 4
A21: Shop Foreman (S10) | B21: ='Labor Costs Worksheet'!AR35 -> 76.75 | C21: ='Labor Costs Worksheet'!AS35 -> 104.71 | D21: 0.05 | E21: =IFERROR(IF(D21="","",+B21*40+(Hours_Per_week-40)*C21)*D21,"") -> 153.5 | F21: =IF(D21="","",+D21*Hours_Per_week) -> 2
A22: Shop Insulator | B22: ='Labor Costs Worksheet'!AT35 -> 41.13 | C22: ='Labor Costs Worksheet'!AU35 -> 57.94 | D22: 0.2 | E22: =IFERROR(IF(D22="","",+B22*40+(Hours_Per_week-40)*C22)*D22,"") -> 329.04 | F22: =IF(D22="","",+D22*Hours_Per_week) -> 8 | H22: Wage | I22: =_xlfn.XLOOKUP(Project_Wage_Rate,Wage_Rate_List,Wage_Rate) -> 30
A23: Warehouseman | B23: ='Labor Costs Worksheet'!AV35 -> 32.76 | C23: ='Labor Costs Worksheet'!AW35 -> 44.49 | E23: =IFERROR(IF(D23="","",+B23*40+(Hours_Per_week-40)*C23)*D23,"") | F23: =IF(D23="","",+D23*Hours_Per_week) | H23: Fringe | I23: =_xlfn.XLOOKUP(Project_Wage_Rate,Wage_Rate_List,Wage_Rate_Fringe) -> 7.29
A24: Totals | D24: =SUM(D3:D23) -> 2.45 | E24: =SUM(E3:E23) -> 5063.58 | F24: =SUM(F3:F23) -> 98 | H24: Totals | I24: =_xlfn.XLOOKUP(Project_Wage_Rate,Wage_Rate_List,Wage_Rate_Total) -> 37.29
F25: =ROUNDUP(+E24/F24,1) -> 51.7

Sheet Labor Costs Worksheet
B1: =CONCATENATE(_xlfn.XLOOKUP('Labor Costs'!I$24,Wage_Rate_Total,Wage_Rate_Year)," - CBA Wage Rate") -> NON-SCALE - CBA Wage Rate | E1: COST OF LABOR CALCULATOR | BK1: Asbestos Insulation Worker | BM1: Working Asbestos Insulation Foreman (S5) | BO1: Project Manager (S10) | BQ1: Safety Inspector (S5) | BS1: Quality Control Inspector (S10) | BU1: Shop Foreman (S10) | BW1: Shop Insulator | BY1: Warehouseman
B2: Next rate increase on: | C2: =_xlfn.XLOOKUP(Project_Wage_Rate,Wage_Rate_List,Wage_As_of) -> 46084 | BF2: ---- | BH2: Hrs in Year (52 weeks x 40 hrs) | BJ2: Hrs | BK2: 2080 | BM2: 2080 | BO2: 2080 | BQ2: 2080 | BS2: 2080 | BU2: 2080 | BW2: 2080 | BY2: 2080
B3: Wage | C3: ='Labor Costs'!I22 -> 30 | BF3: YES | BH3: Paid Holiday ("+A") | BJ3: Hrs | BK3: -72 | BM3: -72 | BO3: -72 | BQ3: -72 | BS3: -72 | BU3: -72 | BW3: -72 | BY3: -72
B4: Fringe | C4: ='Labor Costs'!I23 -> 7.29 | E4: CBA Fringe | F4: 7.29 | H4: Asbestos Insulation Worker | J4: Non-Scale Worker | L4: Working Asbestos Insulation Foreman (S5) | N4: Working Asbestos Insulation Foreman (S4) | P4: Working Asbestos Insulation Foreman (S3) | R4: Working Asbestos Insulation Foreman (S2) | T4: Working Asbestos Insulation Foreman (S1) | V4: Project Manager (S10) | X4: Safety Inspector (S5) | Z4: Asbestos Apprentice Step 1 | AB4: Asbestos Apprentice Step 2 | AD4: Asbestos Apprentice Step 3 | AF4: Asbestos Apprentice Step 4 | AH4: Asbestos Apprentice Step 5 | AJ4: Asbestos Apprentice Step 6 | AL4: Asbestos Apprentice Step 7 | AN4: Asbestos Apprentice Step 8 | AP4: Ops Manager | AR4: Shop Foreman (S10) | AT4: Shop Insulator | AV4: Warehouseman | BF4: NO | BH4: Paid Sick, Personal Days | BJ4: Hrs | BK4: -56 | BM4: -56 | BO4: -56 | BQ4: -80 | BS4: -80 | BU4: -80 | BW4: -80 | BY4: -80
B5: Total | C5: ='Labor Costs'!I24 -> 37.29 | H5: 1 | J5: 1 | L5: 1 | N5: 1 | P5: 1 | R5: 1 | T5: 1 | V5: 1 | X5: 1 | Z5: 0.4 | AB5: 0.45 | AD5: 0.5 | AF5: 0.55 | AH5: 0.6 | AJ5: 0.65 | AL5: 0.7 | AN5: 0.8 | AP5: 1 | AR5: 1 | AT5: 1 | AV5: 1
H6: Reg | I6: OT | J6: Reg | K6: OT | L6: Reg | M6: OT | N6: Reg | O6: OT | P6: Reg | Q6: OT | R6: Reg | S6: OT | T6: Reg | U6: OT | V6: Reg | W6: OT | X6: Reg | Y6: OT | Z6: Reg | AA6: OT | AB6: Reg | AC6: OT | AD6: Reg | AE6: OT | AF6: Reg | AG6: OT | AH6: Reg | AI6: OT | AJ6: Reg | AK6: OT | AL6: Reg | AM6: OT | AN6: Reg | AO6: OT | AP6: Reg | AQ6: OT | AR6: Reg | AS6: OT | AT6: Reg | AU6: OT | AV6: Reg | AW6: OT | BH6: Hrs per year / Basis of Benefits | BJ6: Hrs | BK6: =SUM(BK2:BK4) -> 1952 | BM6: =SUM(BM2:BM4) -> 1952 | BO6: =SUM(BO2:BO4) -> 1952 | BQ6: =SUM(BQ2:BQ4) -> 1928 | BS6: =SUM(BS2:BS4) -> 1928 | BU6: =SUM(BU2:BU4) -> 1928 | BW6: =SUM(BW2:BW4) -> 1928 | BY6: =SUM(BY2:BY4) -> 1928
B7: ='Base Bid'!$B$8 -> NON-SCALE - W: ($30 + F: $7.29) = Total of $37.29 | H7: =+H8+H25 -> 37.29 | I7: =+I8+I25 -> 52.29 | J7: =+J8+J25 -> 37.29 | K7: =+K8+K25 -> 52.29 | L7: =+L8+L25 -> 63 | M7: =+M8+M25 -> 88.355 | N7: =+N8+N25 -> 62 | O7: =+O8+O25 -> 87.355 | ... AW7: =+AW8+AW25 -> 40.29
B8: WAGE - Taxable Wages & Taxable Fringes (See Below) | H8: =SUM(H9:H11) -> 30 | I8: =SUM(I9:I11) -> 45 | J8: =SUM(J9:J11) -> 30 | K8: =SUM(K9:K11) -> 45 | L8: =SUM(L9:L11) -> 55.71 | M8: =SUM(M9:M11) -> 81.065 | N8: =SUM(N9:N11) -> 54.71 | O8: =SUM(O9:O11) -> 80.065 | ... AW8: =SUM(AW9:AW11) -> 33
B9: Direct Labor Rate based on CBA (Actual for Individual or Average Rate for Typical Crew) | H9: =+'Labor Costs'!$I$22 -> 30 | I9: =+H9*1.5 -> 45 | J9: =+'Base Bid'!N5 -> 30 | K9: =+J9*1.5 -> 45 | L9: =IF(IF((Project_wage*L5+7.29)>26.96,Project_wage*L5,19.34)<Base_Rate_Wage,Base_Rate_Wage,IF((Project_wage*L5+7.29)>26.96,Project_wage*L5,19.34)) -> 50.71 | M9: =+L9*1.5 -> 76.065 | N9: =IF(IF((Project_wage*N5+7.29)>26.96,Project_wage*N5,19.34)<Base_Rate_Wage,Base_Rate_Wage,IF((Project_wage*N5+7.29)>26.96,Project_wage*N5,19.34)) -> 50.71 | O9: =+N9*1.5 -> 76.065 | P9: =IF(IF((Project_wage*P5+7.29)>26.96,Project_wage*P5,19.34)<Base_Rate_Wage,Base_Rate_Wage,IF((Project_wage*P5+7.29)>26.96,Project_wage*P5,19.34)) -> 50.71 | Q9: =+P9*1.5 -> 76.065 | R9: =IF((Project_wage*R5+7.29)>26.96,Project_wage*R5,19.34) -> 30 | S9: =+R9*1.5 -> 45 | T9: =IF((Project_wage*T5+7.29)>26.96,Project_wage*T5,19.34) -> 30 | U9: =+T9*1.5 -> 45 | V9: =IF(IF((Project_wage*V5+7.29)>26.96,Project_wage*V5,19.34)<Base_Rate_Wage,Base_Rate_Wage,IF((Project_wage*V5+7.29)>26.96,Project_wage*V5,19.34)) -> 50.71 | W9: =+V9*1.5 -> 76.065 | X9: =IF(IF((Project_wage*X5+7.29)>26.96,Project_wage*X5,19.34)<Base_Rate_Wage,Base_Rate_Wage,IF((Project_wage*X5+7.29)>26.96,Project_wage*X5,19.34)) -> 50.71 | Y9: =+X9*1.5 -> 76.065 | Z9: =IF((Project_wage*Z5+7.29)>26.96,Project_wage*Z5,19.34) -> 19.34 | AA9: =+Z9*1.5 -> 29.01 | AB9: =IF((Project_wage*AB$5+Wage_CBA_Fringe)>(19/0.965+Wage_CBA_Fringe),Project_wage*AB$5,19/0.965) -> 19.689119 | AC9: =+AB9*1.5 -> 29.533679 | AD9: =IF((Project_wage*AD$5+Wage_CBA_Fringe)>(19/0.965+Wage_CBA_Fringe),Project_wage*AD$5,19/0.965) -> 19.689119 | AE9: =+AD9*1.5 -> 29.533679 | AF9: =IF((Project_wage*AF$5+Wage_CBA_Fringe)>(19/0.965+Wage_CBA_Fringe),Project_wage*AF$5,19/0.965) -> 19.689119 | AG9: =+AF9*1.5 -> 29.533679 | AH9: =IF((Project_wage*AH$5+Wage_CBA_Fringe)>(19/0.965+Wage_CBA_Fringe),Project_wage*AH$5,19/0.965) -> 19.689119 | AI9: =+AH9*1.5 -> 29.533679 | AJ9: =IF((Project_wage*AJ$5+Wage_CBA_Fringe)>(19/0.965+Wage_CBA_Fringe),Project_wage*AJ$5,19/0.965) -> 19.689119 | AK9: =+AJ9*1.5 -> 29.533679 | AL9: =IF((Project_wage*AL$5+Wage_CBA_Fringe)>(19/0.965+Wage_CBA_Fringe),Project_wage*AL$5,19/0.965) -> 21 | AM9: =+AL9*1.5 -> 31.5 | AN9: =IF((Project_wage*AN$5+Wage_CBA_Fringe)>(19/0.965+Wage_CBA_Fringe),Project_wage*AN$5,19/0.965) -> 24 | AO9: =+AN9*1.5 -> 36 | AP9: =IF(IF((Project_wage*AP5+7.29)>26.96,Project_wage*AP5,19.34)<Base_Rate_Wage,Base_Rate_Wage,IF((Project_wage*AP5+7.29)>26.96,Project_wage*AP5,19.34)) -> 50.71 | AQ9: =+AP9*1.5 -> 76.065 | AR9: =IF(IF((Project_wage*AR5+7.29)>26.96,Project_wage*AR5,19.34)<Base_Rate_Wage,Base_Rate_Wage,IF((Project_wage*AR5+7.29)>26.96,Project_wage*AR5,19.34)) -> 50.71 | AS9: =+AR9*1.5 -> 76.065 | AT9: 30 | AU9: =+AT9*1.5 -> 45 | AV9: 22 | AW9: =+AV9*1.5 -> 33
A10: Annual Cap - First | B10: Supervisor/QC/Safety additional over wage | H10: 0 | J10: 0 | L10: 5 | M10: 5 | N10: 4 | O10: 4 | P10: 3 | Q10: 3 | R10: 2 | S10: 2 | T10: 1 | U10: 1 | V10: 10 | W10: 10 | X10: 5 | Y10: 5 | Z10: 0 | AB10: 0 | AD10: 0 | AF10: 0 | AH10: 0 | AJ10: 0 | AL10: 0 | AN10: 0 | AP10: 10 | AQ10: 10 | AR10: 10 | AS10: 10 | AT10: 0 | AV10: 0
B11: Cash as equivelent from unused Fringe Benefits (becomes taxable wages) | H11: =IF(+Project_Wage_and_Fringe*H5-Wage_CBA_Fringe-H9<0,0,+Project_Wage_and_Fringe*H5-Wage_CBA_Fringe-H9) -> 0 | I11: =+'Labor Costs'!$I$23-7.29 -> 0 | L11: =IF(+Project_Wage_and_Fringe*L5-Wage_CBA_Fringe-L9<0,0,+Project_Wage_and_Fringe*L5-Wage_CBA_Fringe-L9) -> 0 | M11: =+'Labor Costs'!$I$23-7.29 -> 0 | N11: =IF(+Project_Wage_and_Fringe*N5-Wage_CBA_Fringe-N9<0,0,+Project_Wage_and_Fringe*N5-Wage_CBA_Fringe-N9) -> 0 | O11: =+'Labor Costs'!$I$23-7.29 -> 0 | P11: =IF(+Project_Wage_and_Fringe*P5-Wage_CBA_Fringe-P9<0,0,+Project_Wage_and_Fringe*P5-Wage_CBA_Fringe-P9) -> 0 | Q11: =+'Labor Costs'!$I$23-7.29 -> 0 | R11: =IF(+Project_Wage_and_Fringe*R5-Wage_CBA_Fringe-R9<0,0,+Project_Wage_and_Fringe*R5-Wage_CBA_Fringe-R9) -> 0 | S11: =+'Labor Costs'!$I$23-7.29 -> 0 | T11: =IF(+Project_Wage_and_Fringe*T5-Wage_CBA_Fringe-T9<0,0,+Project_Wage_and_Fringe*T5-Wage_CBA_Fringe-T9) -> 0 | U11: =+'Labor Costs'!$I$23-7.29 -> 0 | V11: =IF(+Project_Wage_and_Fringe*V5-Wage_CBA_Fringe-V9<0,0,+Project_Wage_and_Fringe*V5-Wage_CBA_Fringe-V9) -> 0 | W11: =+'Labor Costs'!$I$23-7.29 -> 0 | X11: =IF(+Project_Wage_and_Fringe*X5-Wage_CBA_Fringe-X9<0,0,+Project_Wage_and_Fringe*X5-Wage_CBA_Fringe-X9) -> 0 | Y11: =+'Labor Costs'!$I$23-7.29 -> 0 | Z11: =IF(+Project_Wage_and_Fringe*Z5-Wage_CBA_Fringe-Z9<0,0,+Project_Wage_and_Fringe*Z5-Wage_CBA_Fringe-Z9) -> 0 | AA11: =+'Labor Costs'!$I$23-7.29 -> 0 | AB11: =IF(+Project_Wage_and_Fringe*AB5-Wage_CBA_Fringe-AB9<0,0,+Project_Wage_and_Fringe*AB5-Wage_CBA_Fringe-AB9) -> 0 | AC11: =+'Labor Costs'!$I$23-7.29 -> 0 | AD11: =IF(+Project_Wage_and_Fringe*AD5-Wage_CBA_Fringe-AD9<0,0,+Project_Wage_and_Fringe*AD5-Wage_CBA_Fringe-AD9) -> 0 | AE11: =+'Labor Costs'!$I$23-7.29 -> 0 | AF11: =IF(+Project_Wage_and_Fringe*AF5-Wage_CBA_Fringe-AF9<0,0,+Project_Wage_and_Fringe*AF5-Wage_CBA_Fringe-AF9) -> 0 | AG11: =+'Labor Costs'!$I$23-7.29 -> 0 | AH11: =IF(+Project_Wage_and_Fringe*AH5-Wage_CBA_Fringe-AH9<0,0,+Project_Wage_and_Fringe*AH5-Wage_CBA_Fringe-AH9) -> 0 | AI11: =+'Labor Costs'!$I$23-7.29 -> 0 | AJ11: =IF(+Project_Wage_and_Fringe*AJ5-Wage_CBA_Fringe-AJ9<0,0,+Project_Wage_and_Fringe*AJ5-Wage_CBA_Fringe-AJ9) -> 0 | AK11: =+'Labor Costs'!$I$23-7.29 -> 0 | AL11: =IF(+Project_Wage_and_Fringe*AL5-Wage_CBA_Fringe-AL9<0,0,+Project_Wage_and_Fringe*AL5-Wage_CBA_Fringe-AL9) -> 0 | AM11: =+'Labor Costs'!$I$23-7.29 -> 0 | AN11: =IF(+Project_Wage_and_Fringe*AN5-Wage_CBA_Fringe-AN9<0,0,+Project_Wage_and_Fringe*AN5-Wage_CBA_Fringe-AN9) -> 0 | AO11: =+'Labor Costs'!$I$23-7.29 -> 0 | AP11: =IF(+Project_Wage_and_Fringe*AP5-Wage_CBA_Fringe-AP9<0,0,+Project_Wage_and_Fringe*AP5-Wage_CBA_Fringe-AP9) -> 0 | AQ11: =+'Labor Costs'!$I$23-7.29 -> 0 | AR11: =IF(+Project_Wage_and_Fringe*AR5-Wage_CBA_Fringe-AR9<0,0,+Project_Wage_and_Fringe*AR5-Wage_CBA_Fringe-AR9) -> 0 | AS11: =+'Labor Costs'!$I$23-7.29 -> 0 | AT11: 0 | AU11: 0 | AV11: 0 | AW11: 0
B12: Payroll Taxes (See Below) - INDIRECT COSTS | H12: =SUM(H13:H24) -> 3.8374 | I12: =SUM(I13:I24) -> 5.6431 | J12: =SUM(J13:J24) -> 3.8374 | K12: =SUM(K13:K24) -> 5.6431 | L12: =SUM(L13:L24) -> 6.9323698 | M12: =SUM(M13:M24) -> 9.9846047 | N12: =SUM(N13:N24) -> 6.8119898 | O12: =SUM(O13:O24) -> 9.8642247 | ... AW12: =SUM(AW13:AW24) -> 4.19854
B13: Employer Labor Burdon Tax - Medicare Payroll Tax (FICA) | F13: Cap | G13: 0.009 | H13: =+H$8*$G13 -> 0.27 | I13: =+I$8*$G13 -> 0.405 | J13: =+J$8*$G13 -> 0.27 | K13: =+K$8*$G13 -> 0.405 | L13: =+L$8*$G13 -> 0.50139 | M13: =+M$8*$G13 -> 0.729585 | N13: =+N$8*$G13 -> 0.49239 | O13: =+O$8*$G13 -> 0.720585 | ... AW13: =+AW$8*$G13 -> 0.297
F14: 184500
B15: Employer Labor Burdon Tax - Federal Insurance Contributions Act (FICA) - Social Security Tax | F15: Cap | G15: =0.0765-0.009 -> 0.0675 | H15: =+H$8*$G15 -> 2.025 | I15: =+I$8*$G15 -> 3.0375 | J15: =+J$8*$G15 -> 2.025 | K15: =+K$8*$G15 -> 3.0375 | L15: =+L$8*$G15 -> 3.760425 | M15: =+M$8*$G15 -> 5.4718875 | N15: =+N$8*$G15 -> 3.692925 | O15: =+O$8*$G15 -> 5.4043875 | ... AW15: =+AW$8*$G15 -> 2.2275
F16: 184500
B17: Employer Labor Burdon Tax - State Unemployment Taxes (SUTA) (recognizing annual cap at 1000 hrs basis) | E17: Hours in equ per worker | F17: Cap | G17: {=_xlfn.IFS(Project_Company=Goel, _xlfn.XLOOKUP(Project_State, Rate_State, SUTA_GOEL_Rate,””), Project_Company=DCB, _xlfn.XLOOKUP(Project_State, Rate_State, SUTA__DCB__Rate,””), Project_Company=GoelDC, _xlfn.XLOOKUP(Project_State, Rate_State, SUTA_GOEL_DC__Rate,””),TRUE, "")} -> 0.033 | H17: =+SUTA/H8*H8*SUTA_RATE/Hours_per_worker -> 0.198 | I17: =+SUTA/I8*I8*SUTA_RATE/Hours_per_worker -> 0.198 | J17: =+SUTA/J8*J8*SUTA_RATE/Hours_per_worker -> 0.198 | K17: =+SUTA/K8*K8*SUTA_RATE/Hours_per_worker -> 0.198 | L17: =+SUTA/L8*L8*SUTA_RATE/Hours_per_worker -> 0.198 | M17: =+SUTA/M8*M8*SUTA_RATE/Hours_per_worker -> 0.198 | N17: =+SUTA/N8*N8*SUTA_RATE/Hours_per_worker -> 0.198 | O17: =+SUTA/O8*O8*SUTA_RATE/Hours_per_worker -> 0.198 | ... AW17: =+SUTA/AW8*AW8*SUTA_RATE/Hours_per_worker -> 0.198
E18: 1500 | F18: =_xlfn.XLOOKUP(Project_State,Rate_State,SUTA__CAP,"") -> 9000
B19: Employer Labor Burdon Tax - Federal Unemployment Tax Act (FUTA) (recognizing annual cap) | F19: Cap | G19: =_xlfn.XLOOKUP(Project_State,Rate_State,FUTA__Rate) -> 0.006 | H19: =+FUTA/H8*H8*FUTA_RATE/Hours_per_worker -> 0.028 | I19: =+FUTA/I8*I8*FUTA_RATE/Hours_per_worker -> 0.028 | J19: =+FUTA/J8*J8*FUTA_RATE/Hours_per_worker -> 0.028 | K19: =+FUTA/K8*K8*FUTA_RATE/Hours_per_worker -> 0.028 | L19: =+FUTA/L8*L8*FUTA_RATE/Hours_per_worker -> 0.028 | M19: =+FUTA/M8*M8*FUTA_RATE/Hours_per_worker -> 0.028 | N19: =+FUTA/N8*N8*FUTA_RATE/Hours_per_worker -> 0.028 | O19: =+FUTA/O8*O8*FUTA_RATE/Hours_per_worker -> 0.028 | ... AW19: =+FUTA/AW8*AW8*FUTA_RATE/Hours_per_worker -> 0.028
A20: 147000 | F20: 7000
A21: 147000 | B21: Worker's Compensation Insurance If CIPP/OCIP - Does WC coverage does not cover WC for PM, Ops, Safety, QC, and off site fabricators | F21: ='Base Bid'!E8 -> Does O/CCIP cover WC? | G21: =IF('Base Bid'!F8="NO",_xlfn.XLOOKUP(Project_State,Rate_State,WC_Insulation),"0") -> 0.04128 | H21: =IF('Base Bid'!$F8="NO",+H$8*$G21,0) -> 1.2384 | I21: =IF('Base Bid'!$F8="NO",+I$8*$G21,0) -> 1.8576 | J21: =IF('Base Bid'!$F8="NO",+J$8*$G21,0) -> 1.2384 | K21: =IF('Base Bid'!$F8="NO",+K$8*$G21,0) -> 1.8576 | L21: =IF('Base Bid'!$F8="NO",+L$8*$G21,0) -> 2.2997088 | M21: =IF('Base Bid'!$F8="NO",+M$8*$G21,0) -> 3.3463632 | N21: =IF('Base Bid'!$F8="NO",+N$8*$G21,0) -> 2.2584288 | O21: =IF('Base Bid'!$F8="NO",+O$8*$G21,0) -> 3.3050832 | ... U21: =IF('Base Bid'!$F8="NO",+U$8*$G21,0) -> 1.89888 | V21: =+V$8*$G21 -> 2.5061088 | W21: =+W$8*$G21 -> 3.5527632 | X21: =+X$8*$G21 -> 2.2997088 | Y21: =+Y$8*$G21 -> 3.3463632 | Z21: =IF('Base Bid'!$F8="NO",+Z$8*$G21,0) -> 0.7983552 | AA21: =IF('Base Bid'!$F8="NO",+AA$8*$G21,0) -> 1.1975328 | AB21: =IF('Base Bid'!$F8="NO",+AB$8*$G21,0) -> 0.81276684 | AC21: =IF('Base Bid'!$F8="NO",+AC$8*$G21,0) -> 1.2191503 | AD21: =IF('Base Bid'!$F8="NO",+AD$8*$G21,0) -> 0.81276684 | AE21: =IF('Base Bid'!$F8="NO",+AE$8*$G21,0) -> 1.2191503 | AF21: =IF('Base Bid'!$F8="NO",+AF$8*$G21,0) -> 0.81276684 | AG21: =IF('Base Bid'!$F8="NO",+AG$8*$G21,0) -> 1.2191503 | ... AO21: =IF('Base Bid'!$F8="NO",+AO$8*$G21,0) -> 1.48608 | AP21: =+AP$8*$G21 -> 2.5061088 | AQ21: =+AQ$8*$G21 -> 3.5527632 | AR21: =+AR$8*$G21 -> 2.5061088 | AS21: =+AS$8*$G21 -> 3.5527632 | AT21: =+AT$8*$G21 -> 1.2384 | AU21: =+AU$8*$G21 -> 1.8576 | AV21: =+AV$8*$G21 -> 0.90816 | AW21: =+AW$8*$G21 -> 1.36224
A22: 8500 | F22: ='Base Bid'!F8 -> No
A23: 7000 | B23: Employer Labor Burdon Tax - Paid Family Leave act (PFL) - Currently appplicable in DC and in MD effective 1-1-27. | F23: What State is this project in? | G23: =_xlfn.XLOOKUP(Project_State,Rate_State,PFL) -> 0.0026 | H23: =IFERROR(+H$8*$G23,0) -> 0.078 | I23: =IFERROR(+I$8*$G23,0) -> 0.117 | J23: =IFERROR(+J$8*$G23,0) -> 0.078 | K23: =IFERROR(+K$8*$G23,0) -> 0.117 | L23: =IFERROR(+L$8*$G23,0) -> 0.144846 | M23: =IFERROR(+M$8*$G23,0) -> 0.210769 | N23: =IFERROR(+N$8*$G23,0) -> 0.142246 | O23: =IFERROR(+O$8*$G23,0) -> 0.208169 | ... AW23: =IFERROR(+AW$8*$G23,0) -> 0.0858
F24: MD
B25: Untaxed Fringes - Exempt under IRS qualified tax exepmt fringe deductions (See Below) | H25: =SUM(H26:H28) -> 7.29 | I25: =SUM(I26:I28) -> 7.29 | J25: =SUM(J26:J28) -> 7.29 | K25: =SUM(K26:K28) -> 7.29 | L25: =SUM(L26:L28) -> 7.29 | M25: =SUM(M26:M28) -> 7.29 | N25: =SUM(N26:N28) -> 7.29 | O25: =SUM(O26:O28) -> 7.29 | ... AW25: =SUM(AW26:AW28) -> 7.29
B26: Union Savings Program or Company IRA (3% match of Wage) or both | H26: =0.25+0.07 -> 0.32 | I26: =+H26 -> 0.32 | J26: =0.25+0.07 -> 0.32 | K26: =+J26 -> 0.32 | L26: =0.25+0.07 -> 0.32 | M26: =+L26 -> 0.32 | N26: =0.25+0.07 -> 0.32 | O26: =+N26 -> 0.32 | P26: =0.25+0.07 -> 0.32 | Q26: =+P26 -> 0.32 | R26: =0.25+0.07 -> 0.32 | S26: =+R26 -> 0.32 | T26: =0.25+0.07 -> 0.32 | U26: =+T26 -> 0.32 | V26: =0.25+0.07+V8*0.03 -> 2.1413 | W26: =0.25+0.07+W8*0.03 -> 2.90195 | X26: =0.25+0.07+X8*0.03 -> 1.9913 | Y26: =0.25+0.07+Y8*0.03 -> 2.75195 | Z26: =0.25+0.07 -> 0.32 | AA26: =+Z26 -> 0.32 | AB26: =0.25+0.07 -> 0.32 | AC26: =+AB26 -> 0.32 | AD26: =0.25+0.07 -> 0.32 | AE26: =+AD26 -> 0.32 | AF26: =0.25+0.07 -> 0.32 | AG26: =+AF26 -> 0.32 | AH26: =0.25+0.07 -> 0.32 | AI26: =+AH26 -> 0.32 | AJ26: =0.25+0.07 -> 0.32 | AK26: =+AJ26 -> 0.32 | AL26: =0.25+0.07 -> 0.32 | AM26: =+AL26 -> 0.32 | AN26: =0.25+0.07 -> 0.32 | AO26: =+AN26 -> 0.32 | AP26: =0.25+0.07+AP8*0.03 -> 2.1413 | AQ26: =0.25+0.07+AQ8*0.03 -> 2.90195 | AR26: =0.25+0.07+AR8*0.03 -> 2.1413 | AS26: =0.25+0.07+AS8*0.03 -> 2.90195 | AT26: =0.25+0.07 -> 0.32 | AU26: =+AT26 -> 0.32 | AV26: =0.25+0.07 -> 0.32 | AW26: =+AV26 -> 0.32
B27: PPO Health, Vision and Dental Insurance - $2.40 per hr | H27: 2.4 | I27: =+H27 -> 2.4 | J27: 2.4 | K27: =+J27 -> 2.4 | L27: 2.4 | M27: =+L27 -> 2.4 | N27: 2.4 | O27: =+N27 -> 2.4 | P27: 2.4 | Q27: =+P27 -> 2.4 | R27: 2.4 | S27: =+R27 -> 2.4 | T27: 2.4 | U27: =+T27 -> 2.4 | V27: 2.4 | W27: =+V27 -> 2.4 | X27: 2.4 | Y27: =+X27 -> 2.4 | Z27: 2.4 | AA27: =+Z27 -> 2.4 | AB27: 2.4 | AC27: =+AB27 -> 2.4 | AD27: 2.4 | AE27: =+AD27 -> 2.4 | AF27: 2.4 | AG27: =+AF27 -> 2.4 | AH27: 2.4 | AI27: =+AH27 -> 2.4 | AJ27: 2.4 | AK27: =+AJ27 -> 2.4 | AL27: 2.4 | AM27: =+AL27 -> 2.4 | AN27: 2.4 | AO27: =+AN27 -> 2.4 | AP27: 2.4 | AQ27: =+AP27 -> 2.4 | AR27: 2.4 | AS27: =+AR27 -> 2.4 | AT27: 2.4 | AU27: =+AT27 -> 2.4 | AV27: 2.4 | AW27: =+AV27 -> 2.4
B28: Other Fringe Benefits in the Union Collective Bargaining Agreement | H28: =7.29-H27-H26 -> 4.57 | I28: =+H28 -> 4.57 | J28: =7.29-J27-J26 -> 4.57 | K28: =+J28 -> 4.57 | L28: =7.29-L27-L26 -> 4.57 | M28: =+L28 -> 4.57 | N28: =7.29-N27-N26 -> 4.57 | O28: =+N28 -> 4.57 | P28: =7.29-P27-P26 -> 4.57 | Q28: =+P28 -> 4.57 | R28: =7.29-R27-R26 -> 4.57 | S28: =+R28 -> 4.57 | T28: =7.29-T27-T26 -> 4.57 | U28: =+T28 -> 4.57 | V28: =7.29-V27-V26 -> 2.7487 | W28: =+V28 -> 2.7487 | X28: =7.29-X27-X26 -> 2.8987 | Y28: =+X28 -> 2.8987 | Z28: =7.29-Z27-Z26 -> 4.57 | AA28: =+Z28 -> 4.57 | AB28: =7.29-AB27-AB26 -> 4.57 | AC28: =+AB28 -> 4.57 | AD28: =7.29-AD27-AD26 -> 4.57 | AE28: =+AD28 -> 4.57 | AF28: =7.29-AF27-AF26 -> 4.57 | AG28: =+AF28 -> 4.57 | AH28: =7.29-AH27-AH26 -> 4.57 | AI28: =+AH28 -> 4.57 | AJ28: =7.29-AJ27-AJ26 -> 4.57 | AK28: =+AJ28 -> 4.57 | AL28: =7.29-AL27-AL26 -> 4.57 | AM28: =+AL28 -> 4.57 | AN28: =7.29-AN27-AN26 -> 4.57 | AO28: =+AN28 -> 4.57 | AP28: =7.29-AP27-AP26 -> 2.7487 | AQ28: =+AP28 -> 2.7487 | AR28: =7.29-AR27-AR26 -> 2.7487 | AS28: =+AR28 -> 2.7487 | AT28: =7.29-AT27-AT26 -> 4.57 | AU28: =+AT28 -> 4.57 | AV28: =7.29-AV27-AV26 -> 4.57 | AW28: =+AV28 -> 4.57
B29: Company Benefits (See Below) & Other | H29: =SUM(H30:H34) -> 6.5625 | I29: =SUM(I30:I34) -> 6.5625 | J29: =SUM(J30:J34) -> 6.5625 | K29: =SUM(K30:K34) -> 6.5625 | L29: =SUM(L30:L34) -> 6.7469262 | M29: =SUM(M30:M34) -> 6.5625 | N29: =SUM(N30:N34) -> 6.7469262 | O29: =SUM(O30:O34) -> 6.5625 | ... AW29: =SUM(AW30:AW34) -> 0
B30: Laptop Computer with Remote Accesss thru AWS Workspaces ($100 per month) | H30: 0 | J30: 0 | L30: 0 | N30: 0 | P30: 0 | R30: 0 | T30: 0 | V30: =100*12/BO6 -> 0.6147541 | X30: =100*12/BQ6 -> 0.62240664 | Z30: 0 | AB30: 0 | AD30: 0 | AF30: 0 | AH30: 0 | AJ30: 0 | AL30: 0 | AN30: 0 | AP30: =100*12/BS6 -> 0.62240664 | AR30: =100*12/BU6 -> 0.62240664 | AT30: 0 | AV30: 0
B31: Lifts | H31: =Lift_percentage*Lift_cost/160 -> 3.4375 | I31: =Lift_percentage*Lift_cost/160 -> 3.4375 | J31: =Lift_percentage*Lift_cost/160 -> 3.4375 | K31: =Lift_percentage*Lift_cost/160 -> 3.4375 | L31: =Lift_percentage*Lift_cost/160 -> 3.4375 | M31: =Lift_percentage*Lift_cost/160 -> 3.4375 | N31: =Lift_percentage*Lift_cost/160 -> 3.4375 | O31: =Lift_percentage*Lift_cost/160 -> 3.4375 | ... U31: =Lift_percentage*Lift_cost/160 -> 3.4375 | Z31: =Lift_percentage*Lift_cost/160 -> 3.4375 | AA31: =Lift_percentage*Lift_cost/160 -> 3.4375 | AB31: =Lift_percentage*Lift_cost/160 -> 3.4375 | AC31: =Lift_percentage*Lift_cost/160 -> 3.4375 | AD31: =Lift_percentage*Lift_cost/160 -> 3.4375 | AE31: =Lift_percentage*Lift_cost/160 -> 3.4375 | AF31: =Lift_percentage*Lift_cost/160 -> 3.4375 | AG31: =Lift_percentage*Lift_cost/160 -> 3.4375 | ... AO31: =Lift_percentage*Lift_cost/160 -> 3.4375
B32: Parking | H32: =IF(Parking="Yes",Parking_cost/8,"") -> 3.125 | I32: =IF(Parking="Yes",Parking_cost/8,"") -> 3.125 | J32: =IF(Parking="Yes",Parking_cost/8,"") -> 3.125 | K32: =IF(Parking="Yes",Parking_cost/8,"") -> 3.125 | L32: =IF(Parking="Yes",Parking_cost/8,"") -> 3.125 | M32: =IF(Parking="Yes",Parking_cost/8,"") -> 3.125 | N32: =IF(Parking="Yes",Parking_cost/8,"") -> 3.125 | O32: =IF(Parking="Yes",Parking_cost/8,"") -> 3.125 | ... AQ32: =IF(Parking="Yes",Parking_cost/8,"") -> 3.125
B33: Tablet ($30 per month) | H33: 0 | J33: 0 | L33: =30*12/BM6 -> 0.18442623 | N33: =30*12/BO6 -> 0.18442623 | P33: =30*12/BQ6 -> 0.18672199 | R33: =30*12/BS6 -> 0.18672199 | T33: =30*12/BU6 -> 0.18672199 | V33: =95*12/BO6 -> 0.58401639 | X33: =95*12/BQ6 -> 0.59128631 | Z33: 0 | AB33: 0 | AD33: 0 | AF33: 0 | AH33: 0 | AJ33: 0 | AL33: 0 | AN33: 0 | AP33: =95*12/BS6 -> 0.59128631 | AR33: =95*12/BU6 -> 0.59128631 | AT33: 0 | AV33: =95*12/BY6 -> 0.59128631
B34: Vehicle allowance ($600/Month) | H34: 0 | J34: 0 | L34: 0 | N34: 0 | P34: 0 | R34: 0 | T34: 0 | V34: =600*12/BO6 -> 3.6885246 | X34: =600*12/BQ6 -> 3.7344398 | Z34: 0 | AB34: 0 | AD34: 0 | AF34: 0 | AH34: 0 | AJ34: 0 | AL34: 0 | AN34: 0 | AP34: =600*12/BS6 -> 3.7344398 | AR34: 0 | AT34: 0 | AV34: 0
B35: Rate | H35: =ROUNDUP(+H$8+H$12+H$25+H$29,2) -> 47.69 | I35: =ROUNDUP(+I$8+I$12+I$25+I$29,2) -> 64.5 | J35: =ROUNDUP(+J$8+J$12+J$25+J$29,2) -> 47.69 | K35: =ROUNDUP(+K$8+K$12+K$25+K$29,2) -> 64.5 | L35: =ROUNDUP(+L$8+L$12+L$25+L$29,2) -> 76.68 | M35: =ROUNDUP(+M$8+M$12+M$25+M$29,2) -> 104.91 | N35: =ROUNDUP(+N$8+N$12+N$25+N$29,2) -> 75.56 | O35: =ROUNDUP(+O$8+O$12+O$25+O$29,2) -> 103.79 | ... AW35: =ROUNDUP(+AW$8+AW$12+AW$25+AW$29,2) -> 44.49
B36: Premium Over Time Rate | H36: =ROUNDUP(+#REF!-H35,2) -> #REF! | J36: =ROUNDUP(+#REF!-J35,2) -> #REF! | L36: =ROUNDUP(+#REF!-L35,2) -> #REF! | N36: =ROUNDUP(+#REF!-N35,2) -> #REF! | P36: =ROUNDUP(+#REF!-P35,2) -> #REF! | R36: =ROUNDUP(+#REF!-R35,2) -> #REF! | T36: =ROUNDUP(+#REF!-T35,2) -> #REF! | V36: =ROUNDUP(+#REF!-V35,2) -> #REF! | X36: =ROUNDUP(+#REF!-X35,2) -> #REF! | AP36: =ROUNDUP(+#REF!-AP35,2) -> #REF! | AR36: =ROUNDUP(+#REF!-AR35,2) -> #REF! | AT36: =ROUNDUP(+#REF!-AT35,2) -> #REF! | AV36: =ROUNDUP(+#REF!-AV35,2) -> #REF!
B37: Premium Double Time Rate | H37: =ROUNDUP(+#REF!-H35,2) -> #REF! | J37: =ROUNDUP(+#REF!-J35,2) -> #REF! | L37: =ROUNDUP(+#REF!-L35,2) -> #REF! | N37: =ROUNDUP(+#REF!-N35,2) -> #REF! | P37: =ROUNDUP(+#REF!-P35,2) -> #REF! | R37: =ROUNDUP(+#REF!-R35,2) -> #REF! | T37: =ROUNDUP(+#REF!-T35,2) -> #REF! | V37: =ROUNDUP(+#REF!-V35,2) -> #REF! | X37: =ROUNDUP(+#REF!-X35,2) -> #REF! | AP37: =ROUNDUP(+#REF!-AP35,2) -> #REF! | AR37: =ROUNDUP(+#REF!-AR35,2) -> #REF! | AT37: =ROUNDUP(+#REF!-AT35,2) -> #REF! | AV37: =ROUNDUP(+#REF!-AV35,2) -> #REF!
B39: General Liability Insurance due to Revenue Based Insurance due to Environmental Remediation Coverages ($0.00 if Covered by CCIP and it covers Environmental remediation and Polution Liability Policies ) | F39: Does O/CCIP cover GL Env Coverage? | G39: =IF(Startup!I56=FALSE,0.01343,"0") -> 0.01343 | H39: =IF($F40="No",+$G39*H35,0) -> 0.6404767 | J39: =IF($F40="No",+$G39*J35,0) -> 0.6404767 | L39: =IF($F40="No",+$G39*L35,0) -> 1.0298124 | N39: =IF($F40="No",+$G39*N35,0) -> 1.0147708 | P39: =IF($F40="No",+$G39*P35,0) -> 0.9998635 | R39: =IF($F40="No",+$G39*R35,0) -> 0.6731116 | T39: =IF($F40="No",+$G39*T35,0) -> 0.65807 | V39: =IF($F40="No",+$G39*V35,0) -> 1.1220765 | X39: =IF($F40="No",+$G39*X35,0) -> 1.0476743 | AP39: =IF($F40="No",+$G39*AP35,0) -> 1.1228823 | AR39: =IF($F40="No",+$G39*AR35,0) -> 1.0307525 | AT39: =IF($F40="No",+$G39*AT35,0) -> 0.5523759 | AV39: =IF($F40="No",+$G39*AV35,0) -> 0.4399668
F40: NO
B41: Total Rate per hr with GL | H41: =+H35+H39 -> 48.330477 | J41: =+J35+J39 -> 48.330477 | L41: =+L35+L39 -> 77.709812 | N41: =+N35+N39 -> 76.574771 | P41: =+P35+P39 -> 75.449864 | R41: =+R35+R39 -> 50.793112 | T41: =+T35+T39 -> 49.65807 | V41: =+V35+V39 -> 84.672077 | X41: =+X35+X39 -> 79.057674 | AP41: =+AP35+AP39 -> 84.732882 | AR41: =+AR35+AR39 -> 77.780753 | AT41: =+AT35+AT39 -> 41.682376 | AV41: =+AV35+AV39 -> 33.199967
B42: Straight Time Rate with GL | H42: =ROUNDUP(+H$8+H$12+H$25+H$29+H$39,2) -> 48.34 | J42: =ROUNDUP(+J$8+J$12+J$25+J$29+J$39,2) -> 48.34 | L42: =ROUNDUP(+L$8+L$12+L$25+L$29,2) -> 76.68 | N42: =ROUNDUP(+N$8+N$12+N$25+N$29,2) -> 75.56 | P42: =ROUNDUP(+P$8+P$12+P$25+P$29,2) -> 74.45 | R42: =ROUNDUP(+R$8+R$12+R$25+R$29,2) -> 50.12 | T42: =ROUNDUP(+T$8+T$12+T$25+T$29,2) -> 49 | V42: =ROUNDUP(+V$8+V$12+V$25+V$29,2) -> 83.55 | X42: =ROUNDUP(+X$8+X$12+X$25+X$29,2) -> 78.01 | AP42: =ROUNDUP(+AP$8+AP$12+AP$25+AP$29,2) -> 83.61 | AR42: =ROUNDUP(+AR$8+AR$12+AR$25+AR$29,2) -> 76.75 | AT42: =ROUNDUP(+AT$8+AT$12+AT$25+AT$29,2) -> 41.13 | AV42: =ROUNDUP(+AV$8+AV$12+AV$25+AV$29,2) -> 32.76
B43: Over Time Rate with GL | H43: =ROUNDUP(+H$8*1.5+H$25+H$29+H$12*1.5+H$39*1.5,2) -> 65.57 | J43: =ROUNDUP(+J$8*1.5+J$25+J$29+J$12*1.5+J$39*1.5,2) -> 65.57 | L43: =ROUNDUP(+L$8*1.5+L$25+L$29+L$12*1.5,2) -> 108.01 | N43: =ROUNDUP(+N$8*1.5+N$25+N$29+N$12*1.5,2) -> 106.32 | P43: =ROUNDUP(+P$8*1.5+P$25+P$29+P$12*1.5,2) -> 104.65 | R43: =ROUNDUP(+R$8*1.5+R$25+R$29+R$12*1.5,2) -> 68.16 | T43: =ROUNDUP(+T$8*1.5+T$25+T$29+T$12*1.5,2) -> 66.48 | V43: =ROUNDUP(+V$8*1.5+V$25+V$29+V$12*1.5,2) -> 117.67 | X43: =ROUNDUP(+X$8*1.5+X$25+X$29+X$12*1.5,2) -> 109.33 | AP43: =ROUNDUP(+AP$8*1.5+AP$25+AP$29+AP$12*1.5,2) -> 117.73 | AR43: =ROUNDUP(+AR$8*1.5+AR$25+AR$29+AR$12*1.5,2) -> 110.88 | AT43: =ROUNDUP(+AT$8*1.5+AT$25+AT$29+AT$12*1.5,2) -> 58.05 | AV43: =ROUNDUP(+AV$8*1.5+AV$25+AV$29+AV$12*1.5,2) -> 45.2
B44: Double Time Rate - With GL | H44: =ROUNDUP(+H$8*2+H$25+H$29+H$12*2+H$39*2,2) -> 82.81 | J44: =ROUNDUP(+J$8*2+J$25+J$29+J$12*2+J$39*2,2) -> 82.81 | L44: =ROUNDUP(+L$8*2+L$25+L$29+L$12*2,2) -> 139.33 | N44: =ROUNDUP(+N$8*2+N$25+N$29+N$12*2,2) -> 137.09 | P44: =ROUNDUP(+P$8*2+P$25+P$29+P$12*2,2) -> 134.85 | R44: =ROUNDUP(+R$8*2+R$25+R$29+R$12*2,2) -> 86.2 | T44: =ROUNDUP(+T$8*2+T$25+T$29+T$12*2,2) -> 83.96 | V44: =ROUNDUP(+V$8*2+V$25+V$29+V$12*2,2) -> 151.8 | X44: =ROUNDUP(+X$8*2+X$25+X$29+X$12*2,2) -> 140.65 | AP44: =ROUNDUP(+AP$8*2+AP$25+AP$29+AP$12*2,2) -> 151.86 | AR44: =ROUNDUP(+AR$8*2+AR$25+AR$29+AR$12*2,2) -> 145 | AT44: =ROUNDUP(+AT$8*2+AT$25+AT$29+AT$12*2,2) -> 74.97 | AV44: =ROUNDUP(+AV$8*2+AV$25+AV$29+AV$12*2,2) -> 57.64
B45: Premium Over Time Rate - With GL | H45: =ROUNDUP(+H43-H42,2) -> 17.23 | J45: =ROUNDUP(+J43-J42,2) -> 17.23 | L45: =ROUNDUP(+L43-L42,2) -> 31.33 | N45: =ROUNDUP(+N43-N42,2) -> 30.76 | P45: =ROUNDUP(+P43-P42,2) -> 30.2 | R45: =ROUNDUP(+R43-R42,2) -> 18.04 | T45: =ROUNDUP(+T43-T42,2) -> 17.48 | V45: =ROUNDUP(+V43-V42,2) -> 34.12 | X45: =ROUNDUP(+X43-X42,2) -> 31.32 | AP45: =ROUNDUP(+AP43-AP42,2) -> 34.12 | AR45: =ROUNDUP(+AR43-AR42,2) -> 34.13 | AT45: =ROUNDUP(+AT43-AT42,2) -> 16.92 | AV45: =ROUNDUP(+AV43-AV42,2) -> 12.44
B46: Premium Double Time Rate - With GL | H46: =ROUNDUP(+H44-H42,2) -> 34.47 | J46: =ROUNDUP(+J44-J42,2) -> 34.47 | L46: =ROUNDUP(+L44-L42,2) -> 62.65 | N46: =ROUNDUP(+N44-N42,2) -> 61.53 | P46: =ROUNDUP(+P44-P42,2) -> 60.4 | R46: =ROUNDUP(+R44-R42,2) -> 36.08 | T46: =ROUNDUP(+T44-T42,2) -> 34.96 | V46: =ROUNDUP(+V44-V42,2) -> 68.25 | X46: =ROUNDUP(+X44-X42,2) -> 62.64 | AP46: =ROUNDUP(+AP44-AP42,2) -> 68.25 | AR46: =ROUNDUP(+AR44-AR42,2) -> 68.25 | AT46: =ROUNDUP(+AT44-AT42,2) -> 33.84 | AV46: =ROUNDUP(+AV44-AV42,2) -> 24.88
B51: Indirects | H51: =+H12/H7 -> 0.10290695 | I51: =+I12/I7 -> 0.1079193 | J51: =+J12/J7 -> 0.10290695 | K51: =+K12/K7 -> 0.1079193 | L51: =+L12/L7 -> 0.11003762 | M51: =+M12/M7 -> 0.11300554 | N51: =+N12/N7 -> 0.1098708 | O51: =+O12/O7 -> 0.11292112 | ... AW51: =+AW12/AW7 -> 0.10420799
H52: =AVERAGE(H51:AW51) -> 0.10517948 | J52: =AVERAGE(J51:AY51) -> 0.1051678
E65: {=_xlfn.IFS(Project_Company="Goel", _xlfn.XLOOKUP(Project_State, Rate_State, SUTA_GOEL_Rate, ""), Project_Company="DCB", _xlfn.XLOOKUP(Project_State, Rate_State, SUTA_DCB_Rate, ""), Project_Company="GoelDC", _xlfn.XLOOKUP(Project_State, Rate_State, SUTA_Goel_DC_Rate, ""),TRUE, "")}

Sheet Spec - HVAC Pipe
A1: HVAC Pipe | M1: HVAC_System | N1: HVAC_Systems_-_Abbreviations | O1: HVAC_Unit | P1: HVAC_Material_Code | Q1: HVAC_Material_Description | R1: HVAC_Area_Code | S1: HVAC_Area_Name | T1: HVAC_Thickness | U1: HVAC_Pipe_Size
A2: System | B2: Code | C2: Area | D2: Area Code | E2: Insulation | F2: Mike Code | G2: Unit | H2: Start Size | I2: End Size | J2: Thickness | K2: Extra Notes | M2: --- | N2: --- | O2: --- | P2: --- | Q2: --- | R2: --- | S2: --- | T2: --- | U2: ---
A3: AC Condensate | B3: {=_xlfn.XLOOKUP(A3,HVAC_System,HVAC_Systems___Abbreviations)} -> ACD | C3: All | D3: {=_xlfn.XLOOKUP(C3,HVAC_Area_Name,HVAC_Area_Code)} -> XX | E3: Fiberglass with ASJ | F3: {=_xlfn.XLOOKUP(E3,HVAC_Material_Description,HVAC_Material_Code)} -> FGA | G3: {=_xlfn.XLOOKUP(A3,HVAC_System,HVAC_Unit)} -> LF | H3: 0.25 | I3: 2 | J3: 1 | M3: AC Condensate | N3: ACD | O3: LF | P3: CAC | Q3: Cal Sil W/ Canvas | R3: XX | S3: All | T3: 0.25 | U3: 0.25
M4: Advanced Plant Water | N4: APW | O4: LF | P4: CAS | Q4: Cal Sil / Plain | R4: A | S4: Concealed | T4: 0.5 | U4: =+U3+0.125 -> 0.375
M5: Boiler Feed Water | N5: BFW | O5: LF | P5: CSA | Q5: Cal Sil w/ Aluminum | R5: E | S5: Exposed | T5: 0.75 | U5: =+U4+0.125 -> 0.5
M6: Breeching | N6: BRE | O6: LF | P6: CSP | Q6: Cal Sil W/ PVC | R6: M | S6: Mechanical | T6: 1 | U6: =+U5+0.125 -> 0.625
M7: Combustion Air | N7: CA | O7: LF | P7: CSS | Q7: Cal Sil W/ Stainless Steel | R7: O | S7: Outdoors | T7: 1.25 | U7: =+U6+0.125 -> 0.75
M8: Continuous Blowdown | N8: CBD | O8: LF | P8: DWP | Q8: Duct Wrap on Pipe | R8: G | S8: Underground | T8: 1.5 | U8: =+U7+0.125 -> 0.875
M9: Chilled Beam | N9: CHB | O9: LF | P9: FGA | Q9: Fiberglass with ASJ | R9: P | S9: Parking | T9: 1.75 | U9: =+U8+0.125 -> 1
M10: Chilled Water | N10: CHW | O10: LF | P10: FGC | Q10: Fiberglass w/ Canvas | R10: T | S10: Attic | T10: 2 | U10: =+U9+0.125 -> 1.125
M11: Condensor Water | N11: CON | O11: LF | P11: FGP | Q11: Fiberglass w/ PVC | R11: C | S11: Crawlspace | T11: 2.5 | U11: =+U10+0.125 -> 1.25
M12: Dual Temp Piping | N12: DTP | O12: LF | P12: FAL | Q12: Fiberglass w/ Aluminum | R12: W | S12: Wall | T12: 2.75 | U12: =+U11+0.125 -> 1.375
M13: Fuel Oil Piping | N13: FOL | O13: LF | P13: FGS | Q13: Fiberglass w/ Stainless Steel | R13: V | S13: Vertical | T13: 3 | U13: =+U12+0.125 -> 1.5
M14: Geothermal Piping | N14: GEO | O14: LF | P14: FGV | Q14: Fiberglass w/ VIC | R14: U | S14: Under Floor | T14: 3.5 | U14: =+U13+0.25 -> 1.75
M15: Generator Exhaust | N15: GEX | O15: LF | P15: FVC | Q15: Fiberglass w/ VIC / Canvas | R15: I | S15: Vault | T15: 4 | U15: =+U14+0.25 -> 2
M16: Glycol Piping | N16: GLY | O16: LF | P16: FVP | Q16: Fiberglass w/ VIC / PVC | R16: J | S16: Tunnel | T16: 5 | U16: =+U15+0.5 -> 2.5
M17: High Pressure Steam | N17: HPS | O17: LF | P17: FVA | Q17: Fiberglass w/ VIC / Aluminum | R17: K | S17: Trench | T17: 6 | U17: =+U16+0.5 -> 3
M18: Medium Pressure Steam | N18: MPS | O18: LF | P18: FVS | Q18: Fiberglass w/ VIC / Stainless | R18: L | S18: Lagging / Liner | T18: 7 | U18: =+U17+0.5 -> 3.5
M19: Low Pressure Steam | N19: LPS | O19: LF | P19: FLX | Q19: Armaflex | R19: H | S19: Heat Trace | T19: 8 | U19: =+U18+0.5 -> 4
M20: Steam Condensate | N20: SCD | O20: LF | P20: FLC | Q20: Armaflex W/ Canvas | R20: Q | S20: Concealed Double Layer | U20: =+U19+1 -> 5
M21: High Temp Steam Condensate | N21: HSC | O21: LF | P21: FLP | Q21: Armaflex W/ PVC | R21: D | S21: Exposed Double Layer | U21: =+U20+1 -> 6
M22: Medium Temp Steam Condensate | N22: MSC | O22: LF | P22: FLA | Q22: Armaflex W/ Aluminum | R22: S | S22: Mechanical Double Layer | U22: =+U21+1 -> 7
M23: Low Temp Steam Condensate | N23: LSC | O23: LF | P23: FLS | Q23: Armaflex W/ Stainless | R23: F | S23: Outdoor Double Layer | U23: =+U22+1 -> 8
M24: Heat Recovery | N24: HRE | O24: LF | P24: FMG | Q24: Foamglass | R24: B-06 | S24: Protection - Below - 06' ft. | U24: =+U23+1 -> 9
M25: Heat Traced Piping | N25: HTP | O25: LF | P25: FMA | Q25: Foamglass w/ Aluminum | R25: B-08 | S25: Protection - Below - 08' ft. | U25: =+U24+1 -> 10
M26: Hot Water Heating | N26: HWH | O26: LF | P26: FMP | Q26: Foamglass w/ PVC | R26: B-10 | S26: Protection - Below - 10' ft. | U26: =+U25+1 -> 11
M27: Pumped Condensate | N27: PC | O27: LF | P27: FMC | Q27: Foamglass w/ Canvas | R27: B-12 | S27: Protection - Below - 12' ft. | U27: =+U26+1 -> 12
M28: Primary Chilled Water | N28: PCH | O28: LF | P28: FMS | Q28: Foamglass w/ Stainless | R28: B-15 | S28: Protection - Below -15' ft.
M29: Process Cooling Water | N29: PCW | O29: LF | P29: FMV | Q29: Foamglass w/VIC
M30: Refrigerant | N30: REF | P30: FAV | Q30: Foamglass w/VIC/Aluminum
M31: Refrigerant Liquid | N31: RL | P31: FPV | Q31: Foamglass w/VIC/ PVC
M32: Refrigerant Suction | N32: RS | P32: FCV | Q32: Foamglass w/VIC/Canvas
M33: Refrigerant Gas | N33: RG | P33: FSV | Q33: Foamglass w/VIC/Stainless
M34: Secondary Chilled Water | N34: SCH | Q34: Polyiso
M35: Steam Vent | N35: STV
Q62: Phenolic

Sheet Spec - Plumbing
A1: Plumbing | M1: Plumbing_System | N1: Plumbing_Systems_-_Abbreviations | O1: Plumbing_Unit | P1: Plumbing_Material_Code | Q1: Plumbing_Material_Description | R1: Plumbing_Area_Code | S1: Plumbing_Area_Name | T1: Plumbing_Thickness | U1: Plumbing_Pipe_Size
A2: System | B2: Code | C2: Area | D2: Area Code | E2: Insulation | F2: Mike Code | G2: Unit | H2: Start Size | I2: End Size | J2: Thickness | K2: Extra Notes | M2: --- | N2: --- | O2: --- | P2: --- | Q2: --- | R2: --- | S2: --- | T2: --- | U2: ---
A3: Domestic Cold Water | B3: =_xlfn.XLOOKUP(A3,Plumbing_System,Plumbing_Systems___Abbreviations) -> DCW | C3: All | D3: =_xlfn.XLOOKUP(C3,Plumbing_Area_Name,Plumbing_Area_Code) -> XX | E3: Fiberglass with ASJ | F3: =_xlfn.XLOOKUP(E3,Plumbing_Material_Description,Plumbing_Material_Code) -> #VALUE! | G3: =_xlfn.XLOOKUP(A3,Plumbing_System,Plumbing_Unit) -> LF | H3: 0.25 | I3: 2 | J3: 1 | M3: AC Condensate | N3: ACD | O3: LF | P3: CAC | Q3: Cal Sil W/ Canvas | R3: XX | S3: All | T3: 0.25 | U3: 0.25
M4: Domestic Cold Water | N4: DCW | O4: LF | P4: CAS | Q4: Cal Sil / Plain | R4: A | S4: Concealed | T4: 0.5 | U4: =+U3+0.125 -> 0.375
M5: Domestic Hot Water | N5: DHW | O5: LF | P5: CSA | Q5: Cal Sil w/ Aluminum | R5: E | S5: Exposed | T5: 0.75 | U5: =+U4+0.125 -> 0.5
M6: Compressed Air | N6: CA | O6: LF | P6: CSP | Q6: Cal Sil W/ PVC | R6: M | S6: Mechanical | T6: 1 | U6: =+U5+0.125 -> 0.625
M7: Clear Water Waste | N7: CWW | O7: LF | P7: CSS | Q7: Cal Sil W/ Stainless Steel | R7: O | S7: Outdoors | T7: 1.25 | U7: =+U6+0.125 -> 0.75
M8: Fuel Oil Pipe | N8: FOL | O8: LF | P8: DWP | Q8: Duct Wrap on Pipe | R8: G | S8: Underground | T8: 1.5 | U8: =+U7+0.125 -> 0.875
M9: Garage Drain | N9: GD | O9: LF | P9: FGA | Q9: Fiberglass with ASJ | R9: P | S9: Parking | T9: 1.75 | U9: =+U8+0.125 -> 1
M10: High Purity Water | N10: HPW | O10: LF | P10: FGC | Q10: Fiberglass w/ Canvas | R10: T | S10: Attic | T10: 2 | U10: =+U9+0.125 -> 1.125
M11: Heat Traced Piping | N11: HTP | O11: LF | P11: FGP | Q11: Fiberglass w/ PVC | R11: C | S11: Crawlspace | T11: 2.5 | U11: =+U10+0.125 -> 1.25
M12: Laboratory Air | N12: LA | O12: LF | P12: FAL | Q12: Fiberglass w/ Aluminum | R12: W | S12: Wall | T12: 2.75 | U12: =+U11+0.125 -> 1.375
M13: Laboratory Domestic Cold Water | N13: LDC | O13: LF | P13: FGS | Q13: Fiberglass w/ Stainless Steel | R13: V | S13: Vertical | T13: 3 | U13: =+U12+0.125 -> 1.5
M14: Laboratory Domestic Hot Water | N14: LDH | O14: LF | P14: FGV | Q14: Fiberglass w/ VIC | R14: U | S14: Under Floor | T14: 3.5 | U14: =+U13+0.25 -> 1.75
M15: Make up Water | N15: MUW | O15: LF | P15: FVC | Q15: Fiberglass w/ VIC / Canvas | R15: I | S15: Vault | T15: 4 | U15: =+U14+0.25 -> 2
M16: Non Potable Water | N16: NPW | O16: LF | P16: FVP | Q16: Fiberglass w/ VIC / PVC | R16: J | S16: Tunnel | T16: 5 | U16: =+U15+0.5 -> 2.5
M17: Pumped Condensate | N17: PC | O17: LF | P17: FVA | Q17: Fiberglass w/ VIC / Aluminum | R17: K | S17: Trench | T17: 6 | U17: =+U16+0.5 -> 3
M18: P - Traps | N18: PTR | O18: LF | P18: FVS | Q18: Fiberglass w/ VIC / Stainless | R18: L | S18: Lagging / Liner | T18: 7 | U18: =+U17+0.5 -> 3.5
M19: Roof Drain | N19: RFD | O19: LF | P19: FLX | Q19: Armaflex | R19: H | S19: Heat Trace | T19: 8 | U19: =+U18+0.5 -> 4
M20: Reverse Osmosis | N20: RO | O20: LF | P20: FLC | Q20: Armaflex W/ Canvas | R20: Q | S20: Concealed Double Layer | U20: =+U19+1 -> 5
M21: Sanitary Waste | N21: SAN | O21: LF | P21: FLP | Q21: Armaflex W/ PVC | R21: D | S21: Exposed Double Layer | U21: =+U20+1 -> 6
M22: Tempered Water | N22: TEM | O22: LF | P22: FLA | Q22: Armaflex W/ Aluminum | R22: S | S22: Mechanical Double Layer | U22: =+U21+1 -> 7
M23: Vent | N23: VNT | O23: LF | P23: FLS | Q23: Armaflex W/ Stainless | R23: F | S23: Outdoor Double Layer | U23: =+U22+1 -> 8
M24: Vertical Storm Drain | N24: VRD | O24: LF | P24: FMG | Q24: Foamglass | R24: B-06 | S24: Protection - Below - 06' ft. | U24: =+U23+1 -> 9
M25: Secondary Storm | N25: SST | O25: LF | P25: FMA | Q25: Foamglass w/ Aluminum | R25: B-08 | S25: Protection - Below - 08' ft. | U25: =+U24+1 -> 10
M26: Horizontal Storm Drain | N26: HRD | O26: LF | P26: FMP | Q26: Foamglass w/ PVC | R26: B-10 | S26: Protection - Below - 10' ft. | U26: =+U25+1 -> 11
M27: Storm | N27: ST | O27: LF | P27: FMC | Q27: Foamglass w/ Canvas | R27: B-12 | S27: Protection - Below - 12' ft. | U27: =+U26+1 -> 12
M28: Overflow Storm | N28: OFS | O28: LF | P28: FMS | Q28: Foamglass w/ Stainless | R28: B-15 | S28: Protection - Below -15' ft.
M29: Rain Harvest | O29: LF | P29: FMV | Q29: Foamglass w/VIC
P30: FAV | Q30: Foamglass w/VIC/Aluminum
P31: FPV | Q31: Foamglass w/VIC/ PVC
P32: FCV | Q32: Foamglass w/VIC/Canvas
P33: FSV | Q33: Foamglass w/VIC/Stainless
Q34: Polyiso
Q62: Phenolic

Sheet Spec - Duct
A1: MSA | B1: Duct | C1: SF | D1: Medium Pressure Supply Air | H1: Types - Universal | N1: Materials
A2: LSA | B2: Duct | C2: SF | D2: Low Pressure Supply Air | H2: A | I2: Types | J2: Concealed | N2: 175 | O2: Duct | P2: 1.5" 3/4lb Duct Wrap
A3: RET | B3: Duct | C3: SF | D3: Return Air | H3: E | I3: Types | J3: Exposed | N3: 275 | O3: Duct | P3: 2" 3/4lb Duct Wrap
A4: EXH | B4: Duct | C4: SF | D4: Exhaust Air | H4: M | I4: Types | J4: Mechanical | N4: 11 | O4: Duct | P4: 1.5" 1lb Duct Wrap
A5: OSA | B5: Duct | C5: SF | D5: Outside Air | H5: O | I5: Types | J5: Outdoors | N5: 21 | O5: Duct | P5: 2" 1lb Duct Wrap
A6: HRE | B6: Duct | C6: SF | D6: Heat Recovery Exhaust | H6: G | I6: Types | J6: Underground | N6: 115 | O6: Duct | P6: 1.5" 1.5lb Wrap
A7: HRR | B7: Duct | C7: SF | D7: Heat Recovery Return | H7: P | I7: Types | J7: Parking | N7: 215 | O7: Duct | P7: 2" 1.5lb Wrap
A8: KHE | B8: Duct | C8: SF | D8: Kitchen Hood Exhaust | H8: T | I8: Types | J8: Attic | N8: 13A | O8: Duct | P8: 1.5" 3lb Board ASJ
A9: FRD | B9: Duct | C9: SF | D9: Fire Rated Duct | H9: C | I9: Types | J9: Crawlspace | N9: 13F | O9: Duct | P9: 1.5" 3lb Board FSK
A10: STP | B10: Duct | C10: SF | D10: Stairwell Pressurization | H10: W | I10: Types | J10: Wall | N10: 13C | O10: Duct | P10: 1.5" 3lb Board FSK w/Canvas
A11: DOA | B11: Duct | C11: SF | D11: DOAS Supply | H11: V | I11: Types | J11: Vertical | N11: 13P | O11: Duct | P11: 1.5" 3lb Board FSK w/PVC
A12: DOR | B12: Duct | C12: SF | D12: DOAS Return | H12: U | I12: Types | J12: Under Floor | N12: 23A | O12: Duct | P12: 2" 3lb Board ASJ
A13: ERR | B13: Duct | C13: SF | D13: Energy Recovery Return | H13: I | I13: Types | J13: Vault | N13: 23F | O13: Duct | P13: 2" 3lb Board FSK
A14: ERS | B14: Duct | C14: SF | D14: Energy Recovery Supply | H14: J | I14: Types | J14: Tunnel | N14: 23C | O14: Duct | P14: 2" 3lb Board FSK w/Canvas
A15: DWE | B15: Duct | C15: SF | D15: Dish Washer Exhaust | H15: K | I15: Types | J15: Trench | N15: 23P | O15: Duct | P15: 2" 3lb Board FSK w/PVC
A16: MUA | B16: Duct | C16: SF | D16: Make Up Air | H16: L | I16: Types | J16: Lagging / Liner | N16: 16A | O16: Duct | P16: 1.5" 6lb Board ASJ
A17: MAR | B17: Duct | C17: SF | D17: Make up Return Air | H17: H | I17: Types | J17: Heat Trace | N17: 16F | O17: Duct | P17: 1.5" 6lb Board FSK
A18: MXA | B18: Duct | C18: SF | D18: Mixed Air | H18: B | I18: Types | J18: Below -' ft. | N18: 16C | O18: Duct | P18: 1.5" 6lb Board FSK w/Canvas
A19: REL | B19: Duct | C19: SF | D19: Relief Air | H19: Q | I19: Types | J19: Concealed Double Layer | N19: 16P | O19: Duct | P19: 1.5" 6lb Board FSK w/PVC
A20: TRA | B20: Duct | C20: SF | D20: Transfer Air | H20: D | I20: Types | J20: Exposed Double Layer | N20: 26A | O20: Duct | P20: 2" 6lb Board ASJ
H21: S | I21: Types | J21: Mechanical Double Layer | N21: 26F | O21: Duct | P21: 2" 6lb Board FSK
H22: F | I22: Types | J22: Outdoor Double Layer | N22: 26C | O22: Duct | P22: 2" 6lb Board FSK w/Canvas
N23: 26P | O23: Duct | P23: 2" 6lb Board FSK w/PVC
N24: 13O | O24: Duct | P24: 1.5" 3lb Board FSK w/Weather Proof Jacket
N25: 23O | O25: Duct | P25: 2" 3lb Board FSK w/Weather Proof Jacket
N26: 16O | O26: Duct | P26: 1.5" 6lb Board FSK w/Weather Proof Jacket
N27: 26O | O27: Duct | P27: 2" 6lb Board FSK w/Weather Proof Jacket
N28: ATF | O28: Duct | P28: Armatuff
N29: FMW | O29: Duct | P29: Fire Master Wrap
N30: LAG | O30: Duct | P30: Sound Lagging B10 or B20
N31: PT1 | O31: Duct | P31: 1.5" Pipe and Tank
N32: PT2 | O32: Duct | P32: 2" Pipe and Tank
N33: RAA | O33: Duct | P33: Rubber sheet Armaflex

Sheet Quantites and Price from Mike
A1: HYDRONIC Sell Price ----> | E1: =+E2 -> 0 | F1: {=_xlfn.TEXTJOIN(", ",TRUE,IF(HVAC_Qnt="","",HVAC_System_Name_NO_Release))} | G1: {=_xlfn.TEXTJOIN(", ",TRUE,IF(HVAC_Qnt="","",HVAC_System_Name_Release_qnt))} | H1: =IF(HVAC_breakout_no_Quantities="","",CONCATENATE(HVAC_breakout_no_Quantities,," - ",SUM(HVAC_Qnt)," LF"))
A2: =SUM(HVAC_Qnt) -> 0 | D2: LF | E2: =SUM(HVAC_Cost_by_System) -> 0
A3: HVAC Qnt | D3: HVAC Code | E3: Price By system | F3: HVAC SYSTEM | G3: HVAC Unit | H3: HVAC System Name | I3: HVAC System Name NO Release | J3: HVAC System Name Release qnt
D4: ACD | F4: HVAC Pipe | G4: LF | H4: AC Condensate | I4: =IF(ISBLANK(A4),"",CONCATENATE(H4)) | J4: =IF(ISBLANK(A4),"",CONCATENATE(H4," (",ROUNDUP(A4,0)," ",G4,")"))
D5: APW | F5: HVAC Pipe | G5: LF | H5: Advanced Plant Water | I5: =IF(ISBLANK(A5),"",CONCATENATE(H5)) | J5: =IF(ISBLANK(A5),"",CONCATENATE(H5," (",ROUNDUP(A5,0)," ",G5,")"))
D6: BFW | F6: HVAC Pipe | G6: LF | H6: Boiler Feed Water | I6: =IF(ISBLANK(A6),"",CONCATENATE(H6)) | J6: =IF(ISBLANK(A6),"",CONCATENATE(H6," (",ROUNDUP(A6,0)," ",G6,")"))
D7: BRE | F7: HVAC Pipe | G7: LF | H7: Breeching | I7: =IF(ISBLANK(A7),"",CONCATENATE(H7)) | J7: =IF(ISBLANK(A7),"",CONCATENATE(H7," (",ROUNDUP(A7,0)," ",G7,")"))
D8: CA | F8: HVAC Pipe | G8: LF | H8: Combustion Air | I8: =IF(ISBLANK(A8),"",CONCATENATE(H8)) | J8: =IF(ISBLANK(A8),"",CONCATENATE(H8," (",ROUNDUP(A8,0)," ",G8,")"))
D9: CBD | F9: HVAC Pipe | G9: LF | H9: Continuous Blowdown | I9: =IF(ISBLANK(A9),"",CONCATENATE(H9)) | J9: =IF(ISBLANK(A9),"",CONCATENATE(H9," (",ROUNDUP(A9,0)," ",G9,")"))
D10: CHB | F10: HVAC Pipe | G10: LF | H10: Chilled Beam | I10: =IF(ISBLANK(A10),"",CONCATENATE(H10)) | J10: =IF(ISBLANK(A10),"",CONCATENATE(H10," (",ROUNDUP(A10,0)," ",G10,")"))
D11: CHW | F11: HVAC Pipe | G11: LF | H11: Chilled Water | I11: =IF(ISBLANK(A11),"",CONCATENATE(H11)) | J11: =IF(ISBLANK(A11),"",CONCATENATE(H11," (",ROUNDUP(A11,0)," ",G11,")"))
D12: CON | F12: HVAC Pipe | G12: LF | H12: Condensor Water | I12: =IF(ISBLANK(A12),"",CONCATENATE(H12)) | J12: =IF(ISBLANK(A12),"",CONCATENATE(H12," (",ROUNDUP(A12,0)," ",G12,")"))
D13: DTP | F13: HVAC Pipe | G13: LF | H13: Dual Temp Piping | I13: =IF(ISBLANK(A13),"",CONCATENATE(H13)) | J13: =IF(ISBLANK(A13),"",CONCATENATE(H13," (",ROUNDUP(A13,0)," ",G13,")"))
D14: FOL | F14: HVAC Pipe | G14: LF | H14: Fuel Oil Piping | I14: =IF(ISBLANK(A14),"",CONCATENATE(H14)) | J14: =IF(ISBLANK(A14),"",CONCATENATE(H14," (",ROUNDUP(A14,0)," ",G14,")"))
D15: GEO | F15: HVAC Pipe | G15: LF | H15: Geothermal Piping | I15: =IF(ISBLANK(A15),"",CONCATENATE(H15)) | J15: =IF(ISBLANK(A15),"",CONCATENATE(H15," (",ROUNDUP(A15,0)," ",G15,")"))
... D36: STV | F36: HVAC Pipe | G36: LF | H36: Steam Vent | I36: =IF(ISBLANK(A36),"",CONCATENATE(H36)) | J36: =IF(ISBLANK(A36),"",CONCATENATE(H36," (",ROUNDUP(A36,0)," ",G36,")"))
F37: HVAC Pipe | G37: LF | I37: =IF(ISBLANK(A37),"",CONCATENATE(H37)) | J37: =IF(ISBLANK(A37),"",CONCATENATE(H37," (",ROUNDUP(A37,0)," ",G37,")"))
F38: HVAC Pipe | G38: LF | I38: =IF(ISBLANK(A38),"",CONCATENATE(H38)) | J38: =IF(ISBLANK(A38),"",CONCATENATE(H38," (",ROUNDUP(A38,0)," ",G38,")"))
F39: HVAC Pipe | G39: LF | I39: =IF(ISBLANK(A39),"",CONCATENATE(H39)) | J39: =IF(ISBLANK(A39),"",CONCATENATE(H39," (",ROUNDUP(A39,0)," ",G39,")"))
F40: HVAC Pipe | G40: LF | I40: =IF(ISBLANK(A40),"",CONCATENATE(H40)) | J40: =IF(ISBLANK(A40),"",CONCATENATE(H40," (",ROUNDUP(A40,0)," ",G40,")"))
A41: Plumbing Price ----> | E41: =SUM(Plumb_Cost_by_System) -> 1000 | F41: {=_xlfn.TEXTJOIN(", ",TRUE,IF(PLUMB_Qnt="","",PLUMB_System_Name_NO_Release))} | G41: {=_xlfn.TEXTJOIN(", ",TRUE,IF(PLUMB_Qnt="","",PLUMB_System_Name_Release_qnt))} | H41: =IF(Plumbing_breakout_no_Quantities="","",CONCATENATE(Plumbing_breakout_no_Quantities," - ",SUM(PLUMB_Qnt)," LF"))
A42: =SUM(PLUMB_Qnt) -> 0 | D42: LF | E42: =SUM(Plumb_Cost_by_System) -> 1000
A43: PLUMB Qnt | D43: PLUMB Code | E43: Price By system | F43: PLUMB SYSTEM | G43: PLUMB Unit | H43: PLUMB System Name | I43: PLUMB System Name NO Release | J43: PLUMB System Name Release qnt
D44: ACD | F44: Plumbing | G44: LF | H44: AC Condensate | I44: =IF(ISBLANK(A44),"",CONCATENATE(H44)) | J44: =IF(ISBLANK(A44),"",CONCATENATE(H44," (",ROUNDUP(A44,0)," ",G44,")"))
D45: DCW | E45: 1000 | F45: Plumbing | G45: LF | H45: Domestic Cold Water | I45: =IF(ISBLANK(A45),"",CONCATENATE(H45)) | J45: =IF(ISBLANK(A45),"",CONCATENATE(H45," (",ROUNDUP(A45,0)," ",G45,")"))
D46: DHW | F46: Plumbing | G46: LF | H46: Domestic Hot Water | I46: =IF(ISBLANK(A46),"",CONCATENATE(H46)) | J46: =IF(ISBLANK(A46),"",CONCATENATE(H46," (",ROUNDUP(A46,0)," ",G46,")"))
D47: CA | F47: Plumbing | G47: LF | H47: Compressed Air | I47: =IF(ISBLANK(A47),"",CONCATENATE(H47)) | J47: =IF(ISBLANK(A47),"",CONCATENATE(H47," (",ROUNDUP(A47,0)," ",G47,")"))
D48: CWW | F48: Plumbing | G48: LF | H48: Clear Water Waste | I48: =IF(ISBLANK(A48),"",CONCATENATE(H48)) | J48: =IF(ISBLANK(A48),"",CONCATENATE(H48," (",ROUNDUP(A48,0)," ",G48,")"))
D49: FOL | F49: Plumbing | G49: LF | H49: Fuel Oil Pipe | I49: =IF(ISBLANK(A49),"",CONCATENATE(H49)) | J49: =IF(ISBLANK(A49),"",CONCATENATE(H49," (",ROUNDUP(A49,0)," ",G49,")"))
D50: GD | F50: Plumbing | G50: LF | H50: Garage Drain | I50: =IF(ISBLANK(A50),"",CONCATENATE(H50)) | J50: =IF(ISBLANK(A50),"",CONCATENATE(H50," (",ROUNDUP(A50,0)," ",G50,")"))
D51: HPW | F51: Plumbing | G51: LF | H51: High Purity Water | I51: =IF(ISBLANK(A51),"",CONCATENATE(H51)) | J51: =IF(ISBLANK(A51),"",CONCATENATE(H51," (",ROUNDUP(A51,0)," ",G51,")"))
D52: HTP | F52: Plumbing | G52: LF | H52: Heat Traced Piping | I52: =IF(ISBLANK(A52),"",CONCATENATE(H52)) | J52: =IF(ISBLANK(A52),"",CONCATENATE(H52," (",ROUNDUP(A52,0)," ",G52,")"))
D53: LA | F53: Plumbing | G53: LF | H53: Laboratory Air | I53: =IF(ISBLANK(A53),"",CONCATENATE(H53)) | J53: =IF(ISBLANK(A53),"",CONCATENATE(H53," (",ROUNDUP(A53,0)," ",G53,")"))
D54: LDC | F54: Plumbing | G54: LF | H54: Laboratory Domestic Cold Water | I54: =IF(ISBLANK(A54),"",CONCATENATE(H54)) | J54: =IF(ISBLANK(A54),"",CONCATENATE(H54," (",ROUNDUP(A54,0)," ",G54,")"))
D55: LDH | F55: Plumbing | G55: LF | H55: Laboratory Domestic Hot Water | I55: =IF(ISBLANK(A55),"",CONCATENATE(H55)) | J55: =IF(ISBLANK(A55),"",CONCATENATE(H55," (",ROUNDUP(A55,0)," ",G55,")"))
D56: MUW | F56: Plumbing | G56: LF | H56: Make up Water | I56: =IF(ISBLANK(A56),"",CONCATENATE(H56)) | J56: =IF(ISBLANK(A56),"",CONCATENATE(H56," (",ROUNDUP(A56,0)," ",G56,")"))
D57: NPW | F57: Plumbing | G57: LF | H57: Non Potable Water | I57: =IF(ISBLANK(A57),"",CONCATENATE(H57)) | J57: =IF(ISBLANK(A57),"",CONCATENATE(H57," (",ROUNDUP(A57,0)," ",G57,")"))
... D69: OFS | F69: Plumbing | G69: LF | H69: Overflow Storm | I69: =IF(ISBLANK(A69),"",CONCATENATE(H69)) | J69: =IF(ISBLANK(A69),"",CONCATENATE(H69," (",ROUNDUP(A69,0)," ",G69,")"))
F70: Plumbing | G70: LF | I70: =IF(ISBLANK(A70),"",CONCATENATE(H70)) | J70: =IF(ISBLANK(A70),"",CONCATENATE(H70," (",ROUNDUP(A70,0)," ",G70,")"))
F71: Plumbing | G71: LF | I71: =IF(ISBLANK(A71),"",CONCATENATE(H71)) | J71: =IF(ISBLANK(A71),"",CONCATENATE(H71," (",ROUNDUP(A71,0)," ",G71,")"))
F72: Plumbing | I72: =IF(ISBLANK(A72),"",CONCATENATE(H72)) | J72: =IF(ISBLANK(A72),"",CONCATENATE(H72," (",ROUNDUP(A72,0)," ",G72,")"))
F73: Plumbing | I73: =IF(ISBLANK(A73),"",CONCATENATE(H73)) | J73: =IF(ISBLANK(A73),"",CONCATENATE(H73," (",ROUNDUP(A73,0)," ",G73,")"))
A74: DUCT Sell Price ----> | E74: =SUM(Duct_Cost_by_System) -> 0 | F74: {=_xlfn.TEXTJOIN(", ",TRUE,IF(DUCT_Qnt="","",DUCT_System_Name_NO_Release))} | G74: {=_xlfn.TEXTJOIN(", ",TRUE,IF(DUCT_Qnt="","",DUCT_System_Name_Release_qnt))} | H74: =CONCATENATE(Duct_breakout_no_Quantities,," - ",SUM(DUCT_Qnt)," SF") -> - 0 SF
A75: =SUM(DUCT_Qnt) -> 0 | D75: LF | E75: =SUM(Duct_Cost_by_System) -> 0
A76: DUCT Qnt | D76: DUCT Code | E76: Price By system | F76: DUCT SYSTEM | G76: DUCT Unit | H76: DUCT System Name | I76: DUCT System Name NO Release | J76: DUCT System Name Release qnt
D77: MSA | F77: Duct | G77: SF | H77: Medium Pressure Supply Air | I77: =IF(ISBLANK(A77),"",CONCATENATE(H77)) | J77: =IF(ISBLANK(A77),"",CONCATENATE(H77," (",ROUNDUP(A77,0)," ",G77,")"))
D78: LSA | F78: Duct | G78: SF | H78: Low Pressure Supply Air | I78: =IF(ISBLANK(A78),"",CONCATENATE(H78)) | J78: =IF(ISBLANK(A78),"",CONCATENATE(H78," (",ROUNDUP(A78,0)," ",G78,")"))
D79: RET | F79: Duct | G79: SF | H79: Return Air | I79: =IF(ISBLANK(A79),"",CONCATENATE(H79)) | J79: =IF(ISBLANK(A79),"",CONCATENATE(H79," (",ROUNDUP(A79,0)," ",G79,")"))
D80: EXH | F80: Duct | G80: SF | H80: Exhaust Air | I80: =IF(ISBLANK(A80),"",CONCATENATE(H80)) | J80: =IF(ISBLANK(A80),"",CONCATENATE(H80," (",ROUNDUP(A80,0)," ",G80,")"))
D81: OSA | F81: Duct | G81: SF | H81: Outside Air | I81: =IF(ISBLANK(A81),"",CONCATENATE(H81)) | J81: =IF(ISBLANK(A81),"",CONCATENATE(H81," (",ROUNDUP(A81,0)," ",G81,")"))
D82: HRE | F82: Duct | G82: SF | H82: Heat Recovery Exhaust | I82: =IF(ISBLANK(A82),"",CONCATENATE(H82)) | J82: =IF(ISBLANK(A82),"",CONCATENATE(H82," (",ROUNDUP(A82,0)," ",G82,")"))
D83: HRR | F83: Duct | G83: SF | H83: Heat Recovery Return | I83: =IF(ISBLANK(A83),"",CONCATENATE(H83)) | J83: =IF(ISBLANK(A83),"",CONCATENATE(H83," (",ROUNDUP(A83,0)," ",G83,")"))
D84: KHE | F84: Duct | G84: SF | H84: Kitchen Hood Exhaust | I84: =IF(ISBLANK(A84),"",CONCATENATE(H84)) | J84: =IF(ISBLANK(A84),"",CONCATENATE(H84," (",ROUNDUP(A84,0)," ",G84,")"))
D85: FRD | F85: Duct | G85: SF | H85: Fire Rated Duct | I85: =IF(ISBLANK(A85),"",CONCATENATE(H85)) | J85: =IF(ISBLANK(A85),"",CONCATENATE(H85," (",ROUNDUP(A85,0)," ",G85,")"))
D86: STP | F86: Duct | G86: SF | H86: Stairwell Pressurization | I86: =IF(ISBLANK(A86),"",CONCATENATE(H86)) | J86: =IF(ISBLANK(A86),"",CONCATENATE(H86," (",ROUNDUP(A86,0)," ",G86,")"))
D87: DOA | F87: Duct | G87: SF | H87: DOAS Supply | I87: =IF(ISBLANK(A87),"",CONCATENATE(H87)) | J87: =IF(ISBLANK(A87),"",CONCATENATE(H87," (",ROUNDUP(A87,0)," ",G87,")"))
D88: DOR | F88: Duct | G88: SF | H88: DOAS Return | I88: =IF(ISBLANK(A88),"",CONCATENATE(H88)) | J88: =IF(ISBLANK(A88),"",CONCATENATE(H88," (",ROUNDUP(A88,0)," ",G88,")"))
... D96: TRA | F96: Duct | G96: SF | H96: Transfer Air | I96: =IF(ISBLANK(A96),"",CONCATENATE(H96)) | J96: =IF(ISBLANK(A96),"",CONCATENATE(H96," (",ROUNDUP(A96,0)," ",G96,")"))
F97: Duct | I97: =IF(ISBLANK(A97),"",CONCATENATE(H97)) | J97: =IF(ISBLANK(A97),"",CONCATENATE(H97," (",ROUNDUP(A97,0)," ",G97,")"))
F98: Duct | I98: =IF(ISBLANK(A98),"",CONCATENATE(H98)) | J98: =IF(ISBLANK(A98),"",CONCATENATE(H98," (",ROUNDUP(A98,0)," ",G98,")"))
F99: Duct | I99: =IF(ISBLANK(A99),"",CONCATENATE(H99)) | J99: =IF(ISBLANK(A99),"",CONCATENATE(H99," (",ROUNDUP(A99,0)," ",G99,")"))
F100: Duct | I100: =IF(ISBLANK(A100),"",CONCATENATE(H100)) | J100: =IF(ISBLANK(A100),"",CONCATENATE(H100," (",ROUNDUP(A100,0)," ",G100,")"))
A101: EQUIPMENT Sell Price ----> | E101: =SUM(EQUIPMENT_Cost_by_System) -> 0 | F101: {=_xlfn.TEXTJOIN(", ",TRUE,IF(EQUIPMENT_Qnt="","",EQUIPMENT_System_Name_NO_Release))} | G101: {=_xlfn.TEXTJOIN(", ",TRUE,IF(EQUIPMENT_Qnt="","",EQUIPMENT_System_Name_Release_qnt))}
A102: =SUM(EQUIPMENT_Qnt) -> 0 | D102: SF | E102: =SUM(EQUIPMENT_Cost_by_System) -> 0
A103: EQUIPMENT Qnt | D103: EQUIPMENT Code | E103: EQU Price By system | F103: EQUIPMENT SYSTEM | G103: EQUIPMENT Unit | H103: EQUIPMENT System Name | I103: EQU System Name NO Release | J103: EQU System Name Release qnt | K103: General cost
E104: =+A104*K104 -> 0 | F104: Equipment | G104: EA | H104: Expansion Tank | I104: =IF(ISBLANK(A104),"",CONCATENATE(H104)) | J104: =IF(ISBLANK(A104),"",CONCATENATE(H104," (",ROUNDUP(A104,0)," ",G104,")")) | K104: 750
E105: =+A105*K105 -> 0 | F105: Equipment | G105: EA HEAD | H105: Chiller Head | I105: =IF(ISBLANK(A105),"",CONCATENATE(H105)) | J105: =IF(ISBLANK(A105),"",CONCATENATE(H105," (",ROUNDUP(A105,0)," ",G105,")")) | K105: 1000
E106: =+A106*K106 -> 0 | F106: Equipment | G106: EA | H106: Pumps | I106: =IF(ISBLANK(A106),"",CONCATENATE(H106)) | J106: =IF(ISBLANK(A106),"",CONCATENATE(H106," (",ROUNDUP(A106,0)," ",G106,")")) | K106: 2000
E107: =+A107*K107 -> 0 | F107: Equipment | G107: EA UNIT | H107: Chilled Beams | I107: =IF(ISBLANK(A107),"",CONCATENATE(H107)) | J107: =IF(ISBLANK(A107),"",CONCATENATE(H107," (",ROUNDUP(A107,0)," ",G107,")")) | K107: 150
E108: =+A108*K108 -> 0 | F108: Equipment | G108: EA | H108: Chiller | I108: =IF(ISBLANK(A108),"",CONCATENATE(H108)) | J108: =IF(ISBLANK(A108),"",CONCATENATE(H108," (",ROUNDUP(A108,0)," ",G108,")")) | K108: 7500
E109: =+A109*K109 -> 0 | F109: Equipment | G109: EA | H109: Air Separators | I109: =IF(ISBLANK(A109),"",CONCATENATE(H109)) | J109: =IF(ISBLANK(A109),"",CONCATENATE(H109," (",ROUNDUP(A109,0)," ",G109,")")) | K109: 750
E110: =+A110*K110 -> 0 | F110: Equipment | G110: EA | H110: Boilers | I110: =IF(ISBLANK(A110),"",CONCATENATE(H110)) | J110: =IF(ISBLANK(A110),"",CONCATENATE(H110," (",ROUNDUP(A110,0)," ",G110,")")) | K110: 15000
E111: =+A111*K111 -> 0 | F111: Equipment | G111: EA | H111: Heat Exchanger | I111: =IF(ISBLANK(A111),"",CONCATENATE(H111)) | J111: =IF(ISBLANK(A111),"",CONCATENATE(H111," (",ROUNDUP(A111,0)," ",G111,")")) | K111: 5000
E112: =+A112*K112 -> 0 | F112: Equipment | G112: EA | H112: Fan Coil Units | I112: =IF(ISBLANK(A112),"",CONCATENATE(H112)) | J112: =IF(ISBLANK(A112),"",CONCATENATE(H112," (",ROUNDUP(A112,0)," ",G112,")")) | K112: 150
E113: =+A113*K113 -> 0 | F113: Equipment | G113: EA | H113: Buffer Tank | I113: =IF(ISBLANK(A113),"",CONCATENATE(H113)) | J113: =IF(ISBLANK(A113),"",CONCATENATE(H113," (",ROUNDUP(A113,0)," ",G113,")")) | K113: =+K104 -> 750
E114: =+A114*K114 -> 0 | F114: Equipment | I114: =IF(ISBLANK(A114),"",CONCATENATE(H114)) | J114: =IF(ISBLANK(A114),"",CONCATENATE(H114," (",ROUNDUP(A114,0)," ",G114,")"))
E115: =+A115*K115 -> 0 | F115: Equipment | I115: =IF(ISBLANK(A115),"",CONCATENATE(H115)) | J115: =IF(ISBLANK(A115),"",CONCATENATE(H115," (",ROUNDUP(A115,0)," ",G115,")"))
E116: =+A116*K116 -> 0 | F116: Equipment | I116: =IF(ISBLANK(A116),"",CONCATENATE(H116)) | J116: =IF(ISBLANK(A116),"",CONCATENATE(H116," (",ROUNDUP(A116,0)," ",G116,")"))
E117: =+A117*K117 -> 0 | F117: Equipment | I117: =IF(ISBLANK(A117),"",CONCATENATE(H117)) | J117: =IF(ISBLANK(A117),"",CONCATENATE(H117," (",ROUNDUP(A117,0)," ",G117,")"))
A118: VRF Piping | E118: =ROUND(+SUM(E124:E125),0) -> #NAME? | F118: =CONCATENATE("VRF - The total amount of VRF piping to be insulated is: ",VRF_Quantity," LF - of which ~ ",H121,"% gets additional covered in PVC or Metal Jacketing.", E122,"Additional Cost per LF is: $",H122," per LF - As part of any subcontract the total LF of VRF piping must be enumerated. ","The basis of our quantities is: ",D121,"Insulation to be: ",D127) -> #NAME?
A119: =+VRF_Quantity -> 0 | D119: LF | E119: =+SUM(E124:E125) -> #NAME?
A120: Number of Cassettes | F120: Our Guessitmate (LF per Cassette) | H120: =IF(E122='VRF and Lists'!H4,200,150) -> 200
A121: Was piping shown on drawings, given to us by mechanical or estimated by cassette? | D121: Guestimate by Cassette | F121: What percentage receives PVC Exterior or metal Jacketing? | H121: 0.2
A122: Is Liquid Suction to be insulated | E122: VRF Liquid Suction IS to be insulated per spec and not included | F122: Cost per LF without PVC (Labor & Material) | H122: =_xlfn.XLOOKUP(D127,VRF_Thickness,VRF_Pricing) -> #NAME?
A123: Total LF of VRF | D123: =+E120*H120 -> 0 | F123: Cost per LF with PVC (Labor & Material) | H123: =_xlfn.XLOOKUP(D127,VRF_Thickness,VRF_Covered) -> #NAME?
A124: Number of LF - No PVC | D124: =VRF_Quantity*(1-H121) -> 0 | E124: =ROUND(+D124*H122,0) -> #NAME?
A125: Number of LF - With PVC | D125: =+VRF_Quantity*(H121) -> 0 | E125: =ROUND(+D125*H123,0) -> #NAME?
A126: Brand of System | D126: Diaken
A127: Thickness | D127: 3/4" Thickness - Elastomeric

Sheet Proposal Sheet
A1: INSULATION PROPOSAL BREAKDOWN SHEET | C1: Prepared for: | E1: =+Company_Selected -> #REF!
A2: From: | B2: =+Bid_From -> #NAME? | C2: Project: | E2: =+'Base Bid'!D1 -> SCU Replacement Basement to 6th Floor, East & West
B3: - Insulation Scope: Thermal insulation of New Systems as listed attached.
B4: - All insulation will be installed per manufactures recommendations.
B5: - Note: No existing piping and ductwork/plenums is included. Our pricing is contingent upon
B6: work being released with enough time to complete before walls and ceilings are closed up
B7: Ladders Last - 5% | G7: Total
A8: Ductwork (Mechanical Insulation): | G8: =+Duct_Price -> 0
A9: Supply Air, Return Air, Exhaust in unconditioned areas, Outside a
A10: HVAC Piping (Mechanical Insulation): | G10: =+Hyrdonic_Price -> 0
A11: =+'Quantites and Price from Mike'!G1
A13: Plumbing (Mechanical Insulation): | G13: =+Plumbing_Price -> 1000
A14: Domestic Cold Water, Domestic Hot Water, Storm Water
A16: =IF(VRF_Price=0,"","VRF SOW (Mechanical Insulation):") -> #NAME? | G16: =+VRF_Price -> #NAME?
A17: =IF(VRF_Quantity=0,"",VRF_SOW)
A19: Equipment (Mechanical Insulation): | G19: =+Equipment_Price -> 0
A20: Chilled Water Pumps, Condensor Water Pumps, Hydropneumatic Tank,
A21: INCLUDED IN BID PRICE - BREAKOUT | G21: =SUM(F23:F27) -> -2500
A22: # | B22: Scope | C22: Qnt | D22: Unit | E22: Price per Unit | F22: Extended
A23: 1 | B23: Shield | C23: 500 | D23: ea | E23: 5 | F23: =IF(C23="","",C23*E23) -> 2500
A24: 2 | B24: VE 645 | C24: 1 | D24: LS | E24: -5000 | F24: =IF(C24="","",C24*E24) -> -5000
F25: =IF(C25="","",C25*E25)
F26: =IF(C26="","",C26*E26)
F27: =IF(C27="","",C27*E27)
A28: BID PRICE TOTAL | G28: =+G16+G19+G10+G8 -> #NAME?
A30: EXCLUDED OPTIONS/ALTERNATES - NOT IN BID PRICE | G30: Add to Total
A31: # | B31: Scope | C31: Qnt | D31: Unit | E31: Price per Unit | F31: Extended
F32: =IF(C32="","",C32*E32)
F35: =IF(C35="","",C35*E35)
F36: =IF(C36="","",C36*E36)
A37: SPECIAL NOTES
A38: - Pricing is for new Duct and Pipe as well as tie in points only.
A39: PRICING CONFIDENTIALITY
A40: =CONCATENATE('VRF and Lists'!#REF!,'VRF and Lists'!#REF!,'VRF and Lists'!#REF!,'VRF and Lists'!#REF!,'VRF and Lists'!#REF!,'VRF and Lists'!#REF!,'VRF and Lists'!#REF!,'VRF and Lists'!#REF!,'VRF and Lists'!#REF!,'VRF and Lists'!#REF!,'VRF and Lists'!#REF!,CHAR(10),CHAR(10),'VRF and Lists'!#REF!,'VRF and Lists'!#REF!,'VRF and Lists'!#REF!,'VRF and Lists'!#REF!,'VRF and Lists'!#REF!,'VRF and Lists'!#REF!,'VRF and Lists'!#REF!) -> #REF!

Sheet Exclusions
A5: EXCEPTION | F5: INCLUDED | G5: NOT INCLUDED
A6: Sound/Acoustical Lagging | G6: X
A7: Fire rated Enclosures | G7: X
A8: Blank of Panels | G8: X
A9: Victaulic Fittings | G9: X
A10: Underground Piping | G10: X
A11: Pre-insulated Pipe Supports | G11: X
A12: ADA Compliant Undersink protection | G12: X
A13: 180 degree Calsil / Foamglass inserts | G13: X
A14: Saddles & Shields | G14: X
A15: Heat Tracing | G15: X
A16: Fire Stopping | G16: X
A17: Color Coding | G17: X
... A36: Bonds | G36: X
A37: VRF Piping Insulation | F37: =IF(VRF_Price=0,"","X") -> #NAME? | G37: =IF(VRF_Price=0,"X","") -> #NAME?
A38: Paintability of the insulation jacketing: | G38: X
A39: For specifications that state "jacketing shall be paintable"
A40: for pipe or duct or similar on all FSK, ASJ, and PSK jacketing
A41: the jacketing is paintable - however the insulation
A42: manufacturer's will not provide a UL Smoke and Flame rating
A43: warranty for the painted product. The responsibility would be
A44: on the painter and as there are fire and smoke. If it must be
A45: painted manufacturer will warranty insulation but will not
A46: warranty the jacket.
A47: "Ladders Last" - If to be added add 4% to the price | G47: X

Sheet VRF and Lists
A1: VRF Pricing | G1: Percentages | H1: VRF List | I1: VRF Method of determining scope | J1: VRF_Manufacturers | L1: Project Type | M1: Project Start In No Months | N1: Project Duration | O1: System | P1: List | Q1: List of Companies | S1: Bidding Company | W1: 5479 | X1: AS of | Z1: 46079 | AE1: 5183 | AL1: Goel Services, Inc.
A2: VRF Thickness | B2: Base Rate - no adjustments (non scale) | C2: VRF Pricing | D2: VRF Covered | E2: Base Rate Total | F2: 58 | G2: --- | H2: --- | I2: ---- | J2: ---- | L2: ---- | M2: ---- | O2: ---- | Q2: --- | S2: --- | U2: Rate State | V2: PFL | W2: WC Insulation | X2: SSN Rate | Y2: Medicare Rate | Z2: FUTA Rate | AA2: SUTA DCB Rate | AB2: SUTA GOEL DC Rate | AC2: SUTA GOEL Rate | AD2: SUTA CAP | AE2: WC Plumber | AF2: SUTA Rate | AG2: Sales Tax by state | AI2: Preference | AK2: Type Of Building
A3: ---- | C3: ---- | D3: ---- | E3: CBA Fringe | F3: 7.29 | G3: 0 | H3: VRF Liquid Suction is NOT to be insulated per spec and not included | I3: Given by mechanical (Customer Quantities) | J3: Blue Star | L3: Fast Renovation | M3: 6 | N3: 3 | P3: Yes | Q3: {=_xlfn._xlws.SORT(_xlfn.UNIQUE('Base Bid'!#REF!))} -> #REF! | S3: Goel Services, Inc. | U3: ---- | V3: ---- | W3: ---- | X3: ---- | Y3: ---- | Z3: ---- | AA3: ---- | AB3: ---- | AC3: ---- | AD3: ---- | AE3: ---- | AF3: ---- | AG3: ---- | AI3: ---- | AK3: ----
A4: 3/4" Thickness - Elastomeric | B4: 6 | C4: =ROUNDUP($B4*IF(Rate_Wage_YN=Rate_No,1,(1+Rate_Incremental)),1) -> #NAME? | D4: =+C4*(1+VRF_Covered_Rate) -> #NAME? | E4: Base Rate Wage | F4: =+Base_rate_total-CBA_Fringe -> 50.71 | G4: =+G3+0.05 -> 0.05 | H4: VRF Liquid Suction IS to be insulated per spec and not included | I4: Estimated by piping diagrams | J4: Carrier | L4: Slow Renovation | M4: 22 | N4: 5 | O4: =+'Quantites and Price from Mike'!F4 -> HVAC Pipe | P4: No | S4: Delaware Cornerstone Builders, Inc. | U4: VA | V4: 0 | W4: 0.05385 | X4: 0.062 | Y4: 0.0145 | Z4: 0.006 | AA4: 0.033 | AB4: 0.04 | AC4: 0.042 | AD4: 8000 | AE4: 0.0279 | AF4: 0.05 | AG4: 0.053 | AI4: MDOT SDB | AK4: Airport Building
A5: 3/4" Thickness - Fiberglass | B5: 5 | C5: =ROUNDUP($B5*IF(Rate_Wage_YN=Rate_No,1,(1+Rate_Incremental)),1) -> #NAME? | D5: =+C5*(1+VRF_Covered_Rate) -> #NAME? | G5: =+G4+0.05 -> 0.1 | I5: Estimated by Drawings | J5: Chigo | L5: New Construction with deep shoring - large | M5: 22 | N5: 12 | O5: Plumbing | S5: Goel DC, LLC | U5: MD | V5: 0.009 | W5: 0.0847 | X5: 0.062 | Y5: 0.0145 | Z5: 0.006 | AA5: 0.033 | AB5: 0.04 | AC5: 0.033 | AD5: 8500 | AE5: 0.056 | AF5: 0.05 | AG5: 0.06 | AI5: CBE | AK5: Airport Hangar
A6: 3/4" Thickness - Foam Glass | B6: 8 | C6: =ROUNDUP($B6*IF(Rate_Wage_YN=Rate_No,1,(1+Rate_Incremental)),1) -> #NAME? | D6: =+C6*(1+VRF_Covered_Rate) -> #NAME? | G6: =+G5+0.05 -> 0.15 | I6: Excluded | J6: Diaken | L6: New Construction with limited excavation - large | M6: 12 | N6: 12 | O6: Duct | U6: DC | V6: 0.0026 | W6: 0.04128 | X6: 0.062 | Y6: 0.0145 | Z6: 0.006 | AA6: 0.033 | AB6: 0.04 | AC6: 0.076 | AD6: 9000 | AE6: 0.0255 | AF6: 0.05 | AG6: 0.06 | AI6: Prince George's CBB | AK6: Data Center
A7: 1" Thickness - Elastomeric | B7: 8 | C7: =ROUNDUP($B7*IF(Rate_Wage_YN=Rate_No,1,(1+Rate_Incremental)),1) -> #NAME? | D7: =+C7*(1+VRF_Covered_Rate) -> #NAME? | G7: =+G6+0.05 -> 0.2 | I7: Guestimate by Cassette | J7: Electrolux | L7: New Construction with deep shoring - small | M7: 22 | N7: 6 | O7: Equipment | U7: PA | V7: 0 | W7: =MAX(W4:W6,W8:W9) -> 0.0847 | X7: 0.062 | Y7: 0.0145 | Z7: 0.006 | AA7: =MAX(AA$4:AA$6) -> 0.033 | AB7: =MAX(AB$4:AB$6) -> 0.04 | AC7: =MAX(AC$4:AC$6) -> 0.076 | AD7: 10000 | AF7: =MAX(AF4:AF6,AF8:AF9) -> 0.05 | AG7: 0.06 | AI7: Federal SDB | AK7: Data Center - Federal
A8: 1" Thickness - Fiberglass | B8: 7 | C8: =ROUNDUP($B8*IF(Rate_Wage_YN=Rate_No,1,(1+Rate_Incremental)),1) -> #NAME? | D8: =+C8*(1+VRF_Covered_Rate) -> #NAME? | G8: =+G7+0.05 -> 0.25 | J8: Emerson Electric | L8: New Construction with limited excavation small | M8: 12 | N8: 6 | U8: DE | V8: 0.008 | W8: 0.073 | X8: 0.062 | Y8: 0.0145 | Z8: 0.006 | AA8: =MAX(AA$4:AA$6) -> 0.033 | AB8: =MAX(AB$4:AB$6) -> 0.04 | AC8: =MAX(AC$4:AC$6) -> 0.076 | AD8: 10500 | AG8: 0 | AI8: Baltimore MWBOO | AK8: Educational - College
A9: 1" Thickness - Foam Glass | B9: 10 | C9: =ROUNDUP($B9*IF(Rate_Wage_YN=Rate_No,1,(1+Rate_Incremental)),1) -> #NAME? | D9: =+C9*(1+VRF_Covered_Rate) -> #NAME? | G9: =+G8+0.05 -> 0.3 | J9: Fijitsu | L9: Immediate Start | M9: 1 | N9: 3 | U9: NJ | V9: 0 | W9: =MAX(W$4:W$6) -> 0.0847 | X9: 0.062 | Y9: 0.0145 | Z9: 0.006 | AA9: =MAX(AA$4:AA$6) -> 0.033 | AB9: =MAX(AB$4:AB$6) -> 0.04 | AC9: =MAX(AC$4:AC$6) -> 0.076 | AD9: 44800 | AG9: 0.0665 | AI9: Virginia SWAM | AK9: Educational - Elementary School
A10: 1 1/2" Thickness - Elastomeric | B10: 10 | C10: =ROUNDUP($B10*IF(Rate_Wage_YN=Rate_No,1,(1+Rate_Incremental)),1) -> #NAME? | D10: =+C10*(1+VRF_Covered_Rate) -> #NAME? | G10: =+G9+0.05 -> 0.35 | J10: Gree Electric Appliances | L10: Multi Phased Renovation | M10: 6 | N10: 24 | AK10: Educational - High School School
A11: 1 1/2" Thickness - Fiberglass | B11: 9 | C11: =ROUNDUP($B11*IF(Rate_Wage_YN=Rate_No,1,(1+Rate_Incremental)),1) -> #NAME? | D11: =+C11*(1+VRF_Covered_Rate) -> #NAME? | G11: =+G10+0.05 -> 0.4 | J11: Haier | AK11: Educational - Middle School
A12: 1 1/2" Thickness - Foam Glass | B12: 12 | C12: =ROUNDUP($B12*IF(Rate_Wage_YN=Rate_No,1,(1+Rate_Incremental)),1) -> #NAME? | D12: =+C12*(1+VRF_Covered_Rate) -> #NAME? | G12: =+G11+0.05 -> 0.45 | J12: HiSense | AK12: Federal - Agency
A13: 2" Thickness - Elastomeric | B13: 12 | C13: =ROUNDUP($B13*IF(Rate_Wage_YN=Rate_No,1,(1+Rate_Incremental)),1) -> #NAME? | D13: =+C13*(1+VRF_Covered_Rate) -> #NAME? | G13: =+G12+0.05 -> 0.5 | J13: Hitachi | AK13: Federal - GSA
A14: 2" Thickness - Fiberglass | B14: 11 | C14: =ROUNDUP($B14*IF(Rate_Wage_YN=Rate_No,1,(1+Rate_Incremental)),1) -> #NAME? | D14: =+C14*(1+VRF_Covered_Rate) -> #NAME? | G14: =+G13+0.05 -> 0.55 | J14: Ingersol Rand | AK14: Federal - Industrial
A15: 2" Thickness - Foam Glass | B15: 14 | C15: =ROUNDUP($B15*IF(Rate_Wage_YN=Rate_No,1,(1+Rate_Incremental)),1) -> #NAME? | D15: =+C15*(1+VRF_Covered_Rate) -> #NAME? | G15: =+G14+0.05 -> 0.6 | J15: Johnson Controls | AK15: Federal - Medical Research
G16: =+G15+0.05 -> 0.65 | J16: Lennox | AK16: Federal - NSA/FBA/CIA
G17: =+G16+0.05 -> 0.7 | J17: LG | AK17: Federal - USACE/NAVFAC
G18: =+G17+0.05 -> 0.75 | J18: Midea | AK18: Hospital - John Hopkins
A19: Incremental for covered | B19: 0.5 | G19: =+G18+0.05 -> 0.8 | J19: Mitsubishi Electric | AK19: Hospital - NIH
A20: Incremental for wage scale | B20: 0.2 | G20: =+G19+0.05 -> 0.85 | J20: Nortek Air Solution | AK20: Hospital - Other Patient Hospital
G21: =+G20+0.05 -> 0.9 | J21: Panasonic | AK21: Hotel Building
G22: =+G21+0.05 -> 0.95 | J22: Samsung | AK22: Industrial Manufacturing Building
G23: =+G22+0.05 -> 1 | J23: Schneider Electric | AK23: Metro Facility
J24: TCL | AK24: Military
J25: Toshiba | U25: Description | X25: MD | Y25: DC | Z25: VA | AA25: Code | AK25: Mixed Use Development
J26: Trane | U26: Masonry NOC | X26: 13.9 | Y26: 5.6 | Z26: 5.49 | AA26: 5022 | AK26: Museum
J27: Voltas | U27: Plumbing NOC & Drivers | X27: 5.6 | Y27: 2.55 | Z27: 2.79 | AA27: 5183 | AK27: Office Building - County
J28: Whirlpool | U28: Electrical Wiring (Within Bldgs) | X28: 4.93 | Y28: — | Z28: 1.83 | AA28: 5190 | AK28: Office Building - Federal
J29: York | U29: Concrete or Cement Work | X29: 8.81 | Y29: 4.25 | Z29: 3.72 | AA29: 5221 | AK29: Office Building - Medical
J30: Other | U30: Carpentry NOC | X30: 10.45 | Y30: 4.75 | Z30: 3.78 | AA30: 5403 | AK30: Office Building - Military
U31: Asbestos Removal | X31: 13.4 | Y31: 6.83 | Z31: 4.37 | AA31: 5472 | AK31: Office Building - Private
U32: Asbestos Removal NOC | X32: 15.84 | Y32: 5.94 | Z32: 6.61 | AA32: 5473 | AK32: Office Building - State
U33: Painting NOC | X33: 8.34 | Y33: 4.18 | Z33: 4.41 | AA33: 5474 | AK33: Power Plant
U34: Floor Covering | X34: 6.49 | Y34: 2.85 | Z34: 2.49 | AA34: 5478 | AK34: Prison
U35: Insulation NOC | X35: 8.47 | Y35: 4.13 | Z35: 5.39 | AA35: 5479 | AK35: Public
U36: Contractor Executive Sup | X36: 1.56 | Y36: 0.7 | Z36: 0.89 | AA36: 5606 | AK36: Recreational/Community Center
U37: Cleaner – Debris | X37: 7.33 | Y37: 3.45 | Z37: 3.44 | AA37: 5610 | AK37: Warehouse
U38: Excavation | X38: 7.41 | Y38: 4.74 | Z38: 4.74 | AA38: 6217 | AK38: Wastewater Treatement Plant
U39: Construction Yard | X39: 6.32 | Y39: — | Z39: 3.52 | AA39: 8227
U40: Sales | X40: 0.42 | Y40: 0.13 | Z40: 0.42 | AA40: 8742
U41: Clerical | X41: 0.17 | Y41: 0.059 | Z41: — | AA41: 8810
U42: Garbage / Refuse | X42: 17.74 | Y42: 11.01 | Z42: 6.86 | AA42: 9403

Sheet Followup
A1: Company ID | B1: Company Type | C1: Company | D1: Phone | E1: Contact | F1: Email | G1: Fax | H1: Address | I1: City | J1: State | K1: Zip | L1: Pipeline | M1: Company Status | N1: Closing Ratio | O1: Location of Bid List (Website) | P1: Country | Q1: What system do they send bid invites from? | R1: If they email invites (Goel) - What email do they send bid invites to? | S1: User Name (bid invites) - Goel | T1: Password for Bid List - Goel | U1: Do we bid to them? | V1: Do we release breakouts to them? | W1: What amount do we bid to them? | X1: Do we only bid piping to them? | Y1: Do we only bid ductwork to them? | Z1: Do we make them call for pricing as we get no feedback? | AA1: If they email invites (DCB) - What email do they send bid invites to? | AB1: If they email invites (Goel DC) - What email do they send bid invites to? | AC1: User Name (bid invites) - DCB | AD1: Password for Bid List - DCB | AE1: User Name (bid invites) - Goel DC | AF1: Password for Bid List - Goel DC | AG1: Do we bid both piping and duct to them? | AH1: Are they part of an AFL-CIO Affiliated Union? | AI1: What percentage of their insulation work do we get? | AJ1: Who is responsible to update this record? | AK1: When was this record updated? | AL1: Which Captain is responsible to market this client? | AM1: Check Weekly? | AN1: Child Companies
A2: 475 | B2: Mechanical Cont | C2: A.G. PRADA COMPANY INC. | D2: (301) 419-2594 | E2: Pat Prada | F2: hvac@agprada.com | G2: (301) 470-4251 | H2: 12122 Conway Rd | I2: Beltsville | J2: MD | K2: 20705 | L2: $0.00 | N2: 0% | AH2: Yes - Local 602 - Steamfitters
A3: 116 | B3: Mechanical Cont | C3: A.i.r Llc Advanced Indoor Resources | D3: 4103822420 | E3: Martin Knott | F3: mknottjr@theairllc.com | H3: 2801 Sisson Street | I3: Baltimore | J3: MD | K3: 21211 | L3: $0.00 | N3: 0%
A4: 476 | B4: Mechanical Cont | C4: A.I.R. CONDITIONING SERVICES LLC | D4: (301) 789-8952 | E4: Jason Hardesty | F4: aircondserv@yahoo.com | H4: 8610 Kip Dr | I4: Owings | J4: MD | K4: 20736 | L4: $0.00 | N4: 0% | AH4: Yes - Local 602 - Steamfitters
A5: 10 | B5: Mechanical Cont | C5: A.L. Merton (Adrian L. Merton Inc.) | D5: (301) 336-2700 | E5: Michael Merton | F5: mickey@almerton.com | G5: (301) 336-6077 | H5: 9011 E. Hampton Dr., P.o. Box 3570 | I5: Capitol Heights | J5: MD | K5: 20743 | L5: $2,717,130.00 | N5: 0% | Q5: Email | U5: Yes | V5: Yes | W5: 100% | X5: Yes | Y5: Yes | AJ5: Giselis Rodulfo | AK5: 1/2/2024
A6: 165 | B6: Mechanical Cont | C6: A&e Heating And Air Cond Llc | D6: 2026081349 | E6: Andre Marr | F6: aandeheatingandair@gmail.com | H6: 513 11th Street Southeast | I6: Washington | J6: DC | K6: 20003 | L6: $0.00 | N6: 0%
A7: 44 | B7: Mechanical Cont | C7: A&e Plumbing, Inc. | D7: 5713596194 | E7: Vickie Loza - Cruz | F7: vickie@aeplumbing1.com | H7: 7069 Gateway Court | I7: Manassas | J7: MD | K7: 20109 | L7: $0.00 | N7: 0%
A8: 388 | B8: Mechanical Cont | C8: Abbott Mechanical Services, Llc | D8: (419) 460-4315 | L8: $0.00 | N8: 0% | AK8: 1/2/24
A9: 45 | B9: Mechanical Cont | C9: Abc General & Mechanical Services, Inc. | D9: (301) 921-4461 | E9: Vijay Paul | F9: vijay@abcgeneralandmechanical.com | H9: 15732 Crabbs Branch Way | I9: Derwood | J9: MD | K9: 20855 | L9: $1,126,900.00 | N9: 0% | Q9: Email
A10: 342 | B10: Mechanical Cont | C10: Abm | D10: 703-370-5850 | E10: Joseph Stein | F10: joseph.stein@abm.com | H10: 5701 General Washington Drive Suite J | I10: Lincolnia | J10: VA | K10: 22312 | L10: $0.00 | N10: 0%
A11: 48 | B11: Mechanical Cont | C11: Acme Mechanical Contractors Of Virginia, Inc. | D11: (703) 335-2677 | E11: Bid Room | F11: quotes@acmemechanical.com | H11: 8584 Virginia Meadows | I11: Manassas | J11: VA | K11: 20109 | L11: $2,598,040.00 | N11: 0% | Q11: Email | U11: Yes | V11: Yes | W11: 100% | X11: Yes | Y11: Yes | Z11: No | AG11: Yes | AJ11: Giselis Rodulfo
A12: 124 | B12: Mechanical Cont | C12: Advanced Heating And Cooling, Llc | D12: (410) 833-9445 | E12: Estimating Department | F12: bpemberton@advancedhc.com | H12: 212 Business Center Dr | I12: Reisterstown | J12: MD | K12: 21136 | L12: $744,900.00 | N12: 0%
A13: 161 | B13: Mechanical Cont | C13: Aegis Mechanical Corporation | D13: (443) 436-6001 | E13: Barnett Carroll | F13: barnettc@aegismech.com | H13: 2034 Lord Baltimore Drive | I13: Woodlawn | J13: MD | K13: 21244 | L13: $537,050.00 | N13: 0%
A14: 170 | B14: Mechanical Cont | C14: Aim Mechanical (In - House Insulation) | D14: 2673770536 | E14: Contact Needed 1 | H14: 23475 Rock Haven Way | I14: Sterling | J14: VA | K14: 20166 | L14: $121,800.00 | N14: 0%
A15: 395 | B15: Mechanical Cont | C15: Air Mover, Inc. | D15: 703.451.1292 | E15: Contact Needed 1 | H15: 7721 Fullerton Road | I15: Springfield | J15: VA | K15: 22153 | L15: $22,000.00 | N15: 0%
A16: 157 | B16: Mechanical Cont | C16: Al's Twin Air Llc | D16: 202-388-8888 | E16: Stephanie Jordan Venson | F16: sjvenson@ataservices1.com | H16: 1914 Benning Road Northeast | I16: Washington | J16: DC | K16: 20002 | L16: $0.00 | N16: 0%
A17: 477 | B17: Mechanical Cont | C17: ALEUT MANAGEMENT SERVICES, LLC | D17: (719) 262-7177 | E17: Damian J. Guerin | F17: Damian.Guerin@Aleutmgt.com | H17: 5540 Tech Center Dr suite 100 | I17: Colorado Springs | J17: CO | K17: 80919 | L17: $0.00 | N17: 0% | AH17: Yes - Local 602 - Steamfitters
A18: 393 | B18: Mechanical Cont | C18: Aleut O&m Services | D18: 2762443322 | H18: 12355 Sunrise Valley Drive; Suite 300j | I18: Reston | J18: VA | K18: 20191 | L18: $0.00 | N18: 0%
A19: 24 | B19: Mechanical Cont | C19: American Combustion Industries, Inc. (ACI) | D19: (301) 779-3400 | E19: David Grimard | F19: dgrimard@aciindustries.com | H19: 7100 Holladay Tyler Road, Suite 233 | I19: Glenn Dale | J19: MD | K19: 20769 | L19: $2,363,600.00 | N19: 0%
A20: 110 | B20: Mechanical Cont | C20: American Mechanical Services Of Maryland, Llc (AMS) | D20: 301-206-5070 | E20: Wondell Hayton | F20: whayton@amsofusa.com | H20: 13300 Mid Atlantic Boulevard | I20: Laurel | J20: MD | K20: 20708 | L20: $73,000.00 | N20: 0%
A21: 255 | B21: Mechanical Cont | C21: Ams Contractors, Inc. | D21: 7035506957 | E21: Michael Stepp | F21: mstepp@amsconstractors.com | H21: 7211 Telegraph Square Drive | I21: Lorton | J21: VA | K21: 22079 | L21: $885,000.00 | N21: 0%
A22: 54 | B22: Mechanical Cont | C22: Anchor Mechanical | D22: 4104525601 | E22: Tony Schaffer | F22: tschaffer@anchormech.com | H22: 126 Industry Lane #4 | I22: Forest Hill | J22: MD | K22: 21050 | L22: $8,581,270.00 | N22: 0%
A23: 266 | B23: Mechanical Cont | C23: Anderson Mechanical Company | E23: Samuel Owens | F23: sowens@amsihvac.com | L23: $1,852,599,620.00 | N23: 0%
A24: 31 | B24: Mechanical Cont | C24: Ariosa & Company Llc | D24: 4106284215 | E24: Fran Leppert | F24: estimating@ariosaco.net | H24: 16 Stenersen Lane, Suite 3a | I24: Hunt Valley | J24: MD | K24: 21030 | L24: $7,832,607.40 | N24: 0%
A25: 58 | B25: Mechanical Cont | C25: Ark Construction Group | D25: 2025875787 | E25: Randy Perillo, Jr. | F25: rperillo@arkdc.com | H25: 700 K Street Northwest | I25: Washington | J25: DC | K25: 20001 | L25: $0.00 | N25: 0%
A26: 63 | B26: Mechanical Cont | C26: Arriba Mechanical | D26: 4104266080 | H26: 3210 Echodale Avenue | I26: Baltimore | J26: MD | K26: 21214 | L26: $0.00 | N26: 0%
A27: 154 | B27: Mechanical Cont | C27: Artic Innovation Systems Llc | D27: (240) 970-7135 | E27: Rebeca | F27: rebeca@arcticinnovationsystems.com | H27: 317 Soapstone Ln | I27: Silver Spring | J27: MD | K27: 20905 | L27: $0.00 | N27: 0%
A28: 21 | B28: Mechanical Cont | C28: Atlantic Constructions (ACI) | D28: 7034772650 | E28: Xx - Chris Mayes | F28: chris.mayes@atlanticpiping.com | H28: 23430 Rockhaven Way, Suite 170 | I28: Sterling | J28: VA | K28: 20166 | L28: $2,572,150.00 | N28: 0%
A29: 59 | B29: Mechanical Cont | C29: Atlantic Industrial Mechanical Electrical (AIME) | D29: (410) 355-1869 | E29: Gary Czajkowski | F29: gczajkowski@jwfi.com | H29: 5730 Pennington Avenue | I29: Baltimore | J29: MD | K29: 21226 | L29: $0.00 | N29: 0%
A30: 232 | B30: Mechanical Cont | C30: Awa Mechanical, Inc. | D30: 4107883535 | E30: Mark Barksdale | F30: mechplumsys@aol.com | H30: 1445 Rolling Road | I30: Catonsville | J30: MD | K30: 21228 | L30: $0.00 | N30: 0%
A31: 65 | B31: Mechanical Cont | C31: Baldwin Mechanical | D31: 4104833312 | E31: Brian Smyth | F31: brian@baldwinmech.com | H31: 8116 Philadelphia Road | I31: Rosedale | J31: MD | K31: 21237 | L31: $3,689,107.40 | N31: 0%
A32: 87 | B32: Mechanical Cont | C32: Baluch Brothers | D32: 540-434-2589 | E32: David Flick | F32: dflick@blauchbrothers.com | H32: 911 Chicago Avenue | I32: Harrisonburg | J32: VA | K32: 22802 | L32: $0.00 | N32: 0%
A33: 70 | B33: Mechanical Cont | C33: Bauer Mechanical Llc | D33: 4438326020 | E33: Joseph Sheldon | F33: jsheldon@bauermech.com | H33: 2109 Maisel Street | I33: Baltimore | J33: MD | K33: 21230 | L33: $1,986,850.00 | N33: 0%
A34: 211 | B34: Mechanical Cont | C34: Beaver Mechanical Contractors, Inc. | D34: (301) 790-1400 | E34: Contact Needed 1 | H34: 61 W Lee St | I34: Hagerstown | J34: MD | K34: 21740 | L34: $0.00 | N34: 0%
A35: 72 | B35: Mechanical Cont | C35: Bel Air Mechanical | D35: 4101167677 | E35: Ryan O'malley | F35: ryan@bamechanicalllc.com | H35: 4220 Shannon Drive | I35: Baltimore | J35: MD | K35: 21213 | L35: $0.00 | N35: 0%
A36: 75 | B36: Mechanical Cont | C36: Bernward Mechanical And Construction Solutions | D36: (410) 975-5576 | E36: Craig Walker | F36: cwalker@bernwards.com | H36: 836 Ritchie Hwy Suite 1 | I36: Severna Park | J36: MD | K36: 21146 | L36: $7,825,520.00 | N36: 0% | Q36: Email
A37: 349 | B37: Mechanical Cont | C37: Bilman Company, Inc. | D37: 3019489040 | E37: Estimating Dept | F37: bids@bilmin.com | H37: 7411 Lindbergh Drive; Suite A | I37: Gaithersburg | J37: MD | K37: 20879 | L37: $687,750.00 | N37: 0%
A38: 78 | B38: Mechanical Cont | C38: Bion Mechanical, Inc. | D38: 7033311400 | E38: Jerome Sweeney | F38: jsweeney@bionmechanical.com | H38: 11721 Pump Station Way | I38: Manassas | J38: VA | K38: 20109 | L38: $77,000.00 | N38: 0%
A39: 80 | B39: Mechanical Cont | C39: Borlie Mechanical Contracting | D39: (304) 260-0935 | E39: Steve Borlie | F39: sborlie@borliemechanical.com | H39: 5521 Tabler Station Road | I39: Inwood | J39: WV | K39: 25428 | L39: $0.00 | N39: 0% | U39: Yes | V39: No | W39: 100% | X39: No | Y39: No | Z39: No | AG39: Yes | AH39: No - non union | AI39: None so far | AJ39: Giselis Rodulfo
A40: 82 | B40: Mechanical Cont | C40: BPI Mechanical Construction, Inc. | D40: (301) 808-3704 | E40: Xx - Dawn Sparkey | F40: dawns@bpimechanical.com | H40: 9103 Hampton Overlook | I40: Capitol Heights | J40: MD | K40: 20743 | L40: $3,643,220.93 | N40: 0% | U40: Yes | V40: No | W40: 100% | X40: No | Y40: No | Z40: No | AG40: Yes | AH40: No - non union | AI40: 10% - 1 out of 10 awards | AJ40: Giselis Rodulfo
A41: 317 | B41: Mechanical Cont | C41: Bradleigh Mechanical Inc. | D41: (703) 834-1216 | E41: Contact Needed 1 | H41: 114 Oakgrove Rd ste 106 | I41: Sterling | J41: VA | K41: 20166 | L41: $97,950.00 | N41: 0%
A42: 72 | B42: Mechanical Cont | C42: Branair, Inc. | D42: (703) 396-8330 | E42: Alicia Dionizio | F42: aliciad@branair.com | G42: (571) 292-2399 | H42: 11900 Livingston Rd suite 157 | I42: Manassas | J42: VA | K42: 20109 | L42: $398,520.00 | N42: 0% | U42: Yes | V42: No | W42: 110% | X42: No | Y42: No | Z42: No | AG42: Yes | AH42: No - non union | AI42: None so far | AJ42: Giselis Rodulfo
A43: 412 | B43: Mechanical Cont | C43: Breeden Companies | D43: (703) 631-2711 | E43: Lee Carroll | F43: lcarroll3@breedencompanies.com | H43: 8101 Flannery Court | I43: Manassas | J43: VA | K43: 20109 | L43: $0.00 | N43: 0% | U43: Yes | V43: No | W43: 110% | X43: No | Y43: No | Z43: No | AG43: Yes | AH43: No - non union | AI43: 10% - 1 out of 10 awards | AJ43: Giselis Rodulfo
A44: 225 | B44: Mechanical Cont | C44: Brothers Mechanical Inc. (BMI) | D44: (703) 750-3828 | E44: Noel Ayala | F44: noel@hvaccomplete.com | H44: 8394 Terminal Road, Unit A | I44: Lorton | J44: VA | K44: 22079 | L44: $9,687,300.00 | N44: 0% | U44: Yes | V44: No | W44: 110% | X44: No | Y44: No | Z44: Yes | AG44: Yes | AH44: No - non union | AI44: None so far | AJ44: Giselis Rodulfo | AK44: 1-2-2024 | AL44: Wilder Rodriguez Romero | AM44: No
A45: 91 | B45: Mechanical Cont | C45: Calvert Mechanical Solutions | D45: (410) 323-5400 | E45: Marck Nelson | F45: markn@calvertinc.com | G45: (410) 323-0015 | H45: 8801 Mylander Ln | I45: Towson | J45: MD | K45: 21286 | L45: $914,400.00 | N45: 0% | U45: Yes | V45: No | W45: 110% | X45: No | Y45: No | Z45: No | AG45: Yes | AH45: No - non union | AI45: None so far | AJ45: Giselis Rodulfo
A46: 60 | B46: Mechanical Cont | C46: Cambi, Inc. | E46: Robert Ainslie | F46: robert.ainslie@cambi.com | H46: 1903 Corona Avenue | I46: Jasper | J46: AL | K46: 35501 | L46: $0.00 | N46: 0%
A47: 92 | B47: Mechanical Cont | C47: Capitol Boiler Works | D47: (800) 296-6881 | E47: Carlos Valdez | F47: cvaldez@capitolboilerworks.com | H47: 1730 Twin Springs Road, #217 | I47: Baltimore | J47: MD | K47: 21227 | L47: $0.00 | N47: 0% | U47: Yes | V47: No | W47: 120% | X47: No | Y47: No | Z47: Yes | AG47: Yes | AH47: No - non union | AI47: None so far | AJ47: Giselis Rodulfo
A48: 150 | B48: Mechanical Cont | C48: Capitol Contractors | D48: (540) 720-9677 | E48: Hannah Briscoe | F48: hbriscoe@capitolcontractorsinc.com | G48: (540) 720-9676 | H48: 225 Tyler Von Way | I48: Fredericksburg | J48: VA | K48: 22405 | L48: $1,062,900.00 | N48: 0% | O48: https://capitolcontractorsinc.com/jobs-bidding/ | Q48: Website login | U48: Yes | V48: No | W48: 110% | X48: No | Y48: No | Z48: Yes | AG48: Yes | AH48: No - non union | AI48: None so far | AJ48: Giselis Rodulfo | AM48: Yes
A49: 93 | B49: Mechanical Cont | C49: CAPPPS Mechanical | D49: (443) 684-7914 | E49: Brian Capps | F49: bcapps@cappsmechanical.com | G49: (888) 600-1246 | H49: 1435 North Solomons Road | I49: Huntingtown | J49: MD | K49: 20639 | L49: $175,000.00 | N49: 0% | V49: No | W49: 110% | X49: No | Y49: No | Z49: No | AG49: Yes | AH49: No - non union | AI49: None so far | AJ49: Giselis Rodulfo
A50: 323 | B50: Mechanical Cont | C50: Carey's Mechanical Llc | D50: (202) 714-2692 | E50: Mo Hall | F50: mhall@rvcareys.com | H50: 3220 O St NW | I50: Washington | J50: DC | K50: 20007 | L50: $1,901,300.00 | N50: 100% | U50: Yes | V50: No | W50: 120% | X50: No | Y50: No | Z50: No | AG50: Yes | AH50: No - non union | AI50: None so far | AJ50: Giselis Rodulfo
A51: 278 | B51: Mechanical Cont | C51: Central Tech Services (A Fidelity Company) | D51: 8663003779 | E51: Steve Miller | F51: smiller@centraltechservices.com | H51: 9592 Deereco Road | I51: Lutherville - Timonium | J51: MD | K51: 21093 | L51: $0.00 | N51: 0%
A52: 374 | B52: Mechanical Cont | C52: Chambers Mechanical | D52: (717) 942-5977 | H52: 21132 Old York Road | I52: Parkton | J52: MD | K52: 21120 | L52: $0.00 | N52: 0%
A53: 379 | B53: Mechanical Cont | C53: Chappelle Mechanical Inc. | D53: (732) 968-2880 | E53: Chris Chappelle | F53: cmechanical@optonline.net | H53: 105 Fleming Street | I53: Piscataway | J53: NJ | K53: 08854 | L53: $541,425.00 | N53: 0%
A54: 101 | B54: Mechanical Cont | C54: Charles A Klein & Sons | D54: 4105496960 | E54: Ryan Klein | F54: klerya@caklein.com | H54: 5220 Klee Mill Road South | I54: Sykesville | J54: MD | K54: 21784 | L54: $0.00 | N54: 0%
A55: 107 | B55: Mechanical Cont | C55: Chilmar Corporation | D55: 4104265482 | E55: Rich Mosmiller | F55: rich@chilmar.com | H55: 5724 Belair Road | I55: Baltimore | J55: MD | K55: 21206 | L55: $737,900.00 | N55: 0%
A56: 256 | B56: Mechanical Cont | C56: City Wide Mechanical | E56: Jonathan Yordy | F56: jyordy@cwmmd.com | H56: 751 Claggett Road | I56: Sunderland | J56: MD | K56: 20689 | L56: $1,496,950.00 | N56: 0%
A57: 109 | B57: Mechanical Cont | C57: Clark Civil (A Divison Of Clark Construction) | D57: 3017278100 | E57: Ari Goldstein | F57: ari.goldstein@clarkfoundationsllc.com | H57: 7500 Old Georgetown Road | I57: Bethesda | J57: MD | K57: 20814 | L57: $1,533,050.00 | N57: 0%
A58: 402 | B58: Mechanical Cont | C58: Clark Water (a Division Of Clark Construction Group, Llc) | E58: Charles Cima | F58: charles.cima@clarkfoundationsllc.com | H58: 7500 Old Georgetown Road 2nd Floor | I58: Bethesda | J58: MD | K58: 20814 | L58: $0.00 | N58: 0%
A59: 104 | B59: Mechanical Cont | C59: Classic Air Conditioning & Heating | E59: Contact Needed 1 | L59: $162,300.00 | N59: 0%
A60: 112 | B60: Mechanical Cont | C60: Classic Heating & Cooling | D60: +1 586-752-2665 | L60: $0.00 | N60: 0%
A61: 107 | B61: Mechanical Cont | C61: Climate Care Hvac Services | D61: 4109213838 | E61: Steve Smollon | F61: steve@climatecareservices.com | H61: 2129 Baldwin Avenue; Suite 9 | I61: Crofton | J61: MD | K61: 21114 | L61: $415,700.00 | N61: 0%
A62: 205 | B62: Mechanical Cont | C62: Cm Heating & Cooling Mechanical S. | D62: (301) 390-5558 | H62: 5308 Sunnyside Avenue | I62: Beltsville | J62: MD | K62: 20705 | L62: $0.00 | N62: 0%
A63: 152 | B63: Mechanical Cont | C63: Cmes Mechanical & Electrical Solutions | D63: 240-499-7640 | E63: Ricky Mellot | F63: rmellott@cmest.com | H63: 4640 Wedgewood Boulevard | I63: Frederick | J63: MD | K63: 21703 | L63: $13,300.00 | N63: 0%
A64: 68 | B64: Mechanical Cont | C64: Colonialwebb Contractors Company - Baltimore, Md | D64: 8442754172 | H64: 150 Blades Lane; Suite F | I64: Glen Burnie | J64: MD | K64: 21061 | L64: $0.00 | N64: 0%
A65: 69 | B65: Mechanical Cont | C65: Colonialwebb Contractors Company - Chantilly, Va | D65: 7033964920 | H65: 14221 - B Willard Road | I65: Chantilly | J65: VA | K65: 20151 | L65: $0.00 | N65: 0%
A66: 70 | B66: Mechanical Cont | C66: Colonialwebb Contractors Company - Hq | D66: 7578553006 | H66: 2820 Ackley Ave | I66: Henrico | J66: VA | K66: 23228 | L66: $0.00 | N66: 0%
A67: 67 | B67: Mechanical Cont | C67: Comfort Systems Usa | D67: 7138309600 | E67: Daniel Barnhill | F67: Daniel.barnhill@comfortsystemsusa.com | H67: 675 Bering Drive; Suite 400 | I67: Houston | J67: TX | K67: 77057 | L67: $13,100.00 | N67: 0%
A68: 280 | B68: Mechanical Cont | C68: Complete Building Services, Inc. | D68: 2023334977 | E68: Ben Vanderhoof | F68: benv@donohoe.com | H68: 5100 Wisconsin Avenue Northwest; Suite 500 | I68: Washington | J68: DC | K68: 20016 | L68: $0.00 | N68: 0%
A69: 177 | B69: Mechanical Cont | C69: Control Tech Inc | D69: 309-692-1029 | E69: Contact Needed 1 | H69: 8938 North Prairie Point | I69: Peoria | J69: IL | K69: 61615 | L69: $79,600.00 | N69: 0%
A70: 212 | B70: Mechanical Cont | C70: Cool Breeze Hvac, Inc. | D70: (704) 225-3659 | L70: $0.00 | N70: 0%
A71: 50 | B71: Mechanical Cont | C71: Cpf Inc. (Underground Utilities) | D71: 410-535-5210 | E71: Michael Whitney | F71: mikew@cpfuinc.com | H71: 180 Jibsail Drive | I71: Prince Fredrick | J71: MD | L71: $0.00 | N71: 0%
A72: 378 | B72: Mechanical Cont | C72: Craddock Mechanical Llc | I72: Mechanicsville | J72: MD | K72: 20659 | L72: $0.00 | N72: 0%
A73: 123 | B73: Mechanical Cont | C73: Crw Mechanical, Inc. | D73: 3019180056 | E73: Tom Melton | F73: estimating@crwmechanical.com | H73: 5807 Ellerbie Street | I73: Lanham | J73: MD | K73: 20706 | L73: $261,500.00 | N73: 0%
A74: 266 | B74: Mechanical Cont | C74: Cta Consulting Engineers | D74: (301) 762-7172 | H74: 220 North Adams Street | I74: Rockville | J74: MD | K74: 20850 | L74: $0.00 | N74: 0%
A75: 105 | B75: Mechanical Cont | C75: D&i Mechanical Constractors, Inc. | D75: (410) 795-1116 | E75: Matt Jarosinski | F75: matt@dandimechanical.com | G75: (410) 771-1859 | H75: 10815 Beaver Dam Road | I75: Cockeysville | J75: MD | K75: 21030 | L75: $7,000.00 | N75: 0%
A76: 151 | B76: Mechanical Cont | C76: Dc Mechanical, Llc | D76: 571-267-7985 | E76: Stephanie Mabra | F76: stephanie.mabra@dc-mech.com | H76: 21641 Beaumeade Circle | I76: Ashburn | J76: VA | K76: 20147 | L76: $0.00 | N76: 0%
A77: 456 | B77: Mechanical Cont | C77: Domco Mechanical Inc | E77: Estimating | F77: info@domcomech.com | L77: $0.00 | N77: 0%
A78: 37 | B78: Mechanical Cont | C78: Doyle Systems, Llc | D78: 3013176001 | E78: Xx - Ryan Lignelli | F78: rlignelli@doylesystems.com | H78: 10610 Iron Bridge Road, Suite 9 | I78: Jessup | J78: MD | K78: 20794 | L78: $511,800.00 | N78: 0%
A79: 134 | B79: Mechanical Cont | C79: DTSB Technologies - Mechanical | L79: $0.00 | N79: 0%
A80: 153 | B80: Mechanical Cont | C80: Dynamic Mechanical Contractors | D80: 3012527657 | E80: Bill Lauri | F80: wlauri@dmc-mech.com | H80: 11160 Veirs Mill Road; Suite Llh - 18 #240 | I80: Wheaton - Glenmont | J80: MD | K80: 20902 | L80: $3,249,950.00 | N80: 0%
A81: 43 | B81: Mechanical Cont | C81: Dynastics, Inc. | D81: (410) 247-6750 | E81: Dale Gatton | F81: dgatton@dynastics.com | H81: 9351 Philadelphia Rd suite j | I81: Baltimore | J81: MD | K81: 21237 | L81: $0.00 | N81: 0%
A82: 166 | B82: Mechanical Cont | C82: East Coast Heating & Cooling | D82: 443-813-0267 | E82: Cameron Leopold | F82: cleopold@ecoastheatingandcooling.com | H82: 8969 Yellow Brick Road, Ste. A | I82: Middle River | J82: MD | L82: $0.00 | N82: 0%
A83: 139 | B83: Mechanical Cont | C83: Eastern Technical, Inc. | D83: 4108828272 | E83: Tim Napoli | F83: tnapoli@etisvs.com | H83: 915 Middle River Road; Suite E | I83: Middle River | J83: MD | K83: 21220 | L83: $0.00 | N83: 0%
A84: 254 | B84: Mechanical Cont | C84: Elias and Son Plumbing and HVAC | D84: (703) 335-0505 | H84: 8615 Quarry Rd. | I84: Manassas | J84: VA | K84: 20110 | L84: $0.00 | N84: 0%
A85: 426 | B85: Mechanical Cont | C85: Elizabeth River Mechanical | D85: (757) 773-0540 | E85: Jeff Beasley | F85: jbeasley@ermechanical.com | H85: 700 Broad Street | I85: Portsmouth | J85: VA | K85: 23707 | L85: $0.00 | N85: 0%
A86: 197 | B86: Mechanical Cont | C86: Ellington Mechanical Services Inc | D86: 7032201651 | E86: Rob Butler | F86: rbutler@ellingtonmechanical.com | H86: 4605 Emerson Street | I86: Hyattsville | J86: MD | K86: 20781 | L86: $16,800.00 | N86: 0%
A87: 107 | B87: Mechanical Cont | C87: Emcor Group | D87: (866) 890-7794 | H87: 301 Merritt 7 | I87: Norwalk | J87: CT | K87: 06851 | L87: $0.00 | N87: 0%
A88: 108 | B88: Mechanical Cont | C88: Emcor Services Combustioneer - Hq | D88: 301.340.2612 | E88: Jeff Gaddy | F88: jeff.gaddy@combustioneer.com | H88: 4420 Lottsford Vista Road; Suite 1 | I88: Lanham | J88: MD | K88: 20706 | L88: $0.00 | N88: 0%
A89: 298 | B89: Mechanical Cont | C89: Emh Environmental, Inc. | D89: +1 410-489-9630 | E89: Contact Needed 1 | L89: $0.00 | N89: 0%
A90: 144 | B90: Mechanical Cont | C90: Emjay Engineering & Construction Co., Inc. | D90: (410) 298-2000 | E90: Armando Ravera | F90: raveraa@emjaycons.com | G90: (410) 298-2430 | H90: 1706 Whitehead Road | I90: Baltimore | J90: MD | K90: 21207 | L90: $1,885,597.40 | N90: 0%
A91: 354 | B91: Mechanical Cont | C91: Energesco Mechanical | D91: +1 571-932-3590 | E91: Contact Needed 1 | H91: 1000 Cameron St | I91: Alexandria | J91: VA | K91: 22314 | L91: $342,200.00 | N91: 0%
A92: 9 | B92: Mechanical Cont | C92: Excel Mechanical Contractors, Llc | D92: 4439694875 | E92: James Bloom | F92: jbloom@excel-mechanical.com | H92: 4 Nashua Court, Bay 11 | I92: Baltimore | J92: MD | K92: 21211 | L92: $6,796,285.00 | N92: 0%
A93: 374 | B93: Mechanical Cont | C93: Exp Us Services, Inc. | D93: 8044744500 | L93: $0.00 | N93: 0%
A94: 152 | B94: Mechanical Cont | C94: Fidelity Mechanical Services | D94: 4107719400 | E94: Mike Flurry | F94: mflurry@fidelity-ms.com | H94: 25 Loveton Circle | I94: Sparks | J94: MD | K94: 21152 | L94: $514,010.00 | N94: 0%
A95: 414 | B95: Mechanical Cont | C95: Flo-Tron Contracting Inc. | D95: (410) 527-0060 | E95: Contact Needed 1 | H95: 10604 Beaver Dam Rd | I95: Cockeysville | J95: MD | K95: 21030 | L95: $42,800.00 | N95: 0% | U95: Yes
A96: 208 | B96: Mechanical Cont | C96: Freedom Mechanical | D96: (830) 935-4337 | H96: Canyon Lake, Tx 78133 | L96: $0.00 | N96: 0%
A97: 162 | B97: Mechanical Cont | C97: Fresh Air Concepts, LLC | D97: (410) 789-7800 | E97: Joeseph Haycock | F97: joehaycock@gmail.com | H97: 5195 Raynor Avenue | I97: Linthicum Heights | J97: MD | K97: 21090 | L97: $1,403,300.00 | N97: 0% | P97: United States | U97: Yes | V97: No | W97: 130% | X97: No | Y97: No | Z97: Yes
A98: 177 | B98: Mechanical Cont | C98: G.e. Tignall & Co., Inc | D98: 410-666-3000 | E98: Mike Harper | F98: mharper@getignall.com | H98: 14 Mccann Avenue | I98: Hunt Valley | J98: MD | K98: 21030 | L98: $1,578,600.00 | N98: 0%
A99: 163 | B99: Mechanical Cont | C99: G.h. Nitzel, Inc. | D99: 4103350200 | E99: Dave Wilmoth | F99: dave@ghnitzel.com | H99: 11300 Pulaski Hwy | I99: White Marsh | J99: MD | K99: 21162-1526 | L99: $661,950.00 | N99: 0%
A100: 164 | B100: Mechanical Cont | C100: Gaghan Mechanical, Inc. | D100: 7033602471 | E100: Bobby Stovall | F100: bobby@gaghanmech.com | H100: 5208 Cedar Road | I100: Alexandria | J100: VA | K100: 22309 | L100: $1,985,218.27 | N100: 0%
...
